Workbook
Name __aip1: #REF!
Name __aip10: #REF!
Name __aip11: #REF!
Name __aip2: #REF!
Name __aip3: #REF!
Name __aip4: #REF!
Name __aip5: #REF!
Name __aip6: #REF!
Name __aip7: #REF!
Name __aip8: #REF!
Name __aip9: #REF!
Name __FDS_USED_FOR_REUSING_RANGE_IDS_RECYCLE: {19}
Name _20_Jul_94: #REF!
Name _aip1: #REF!
Name _aip10: #REF!
Name _aip11: #REF!
Name _aip2: #REF!
Name _aip3: #REF!
Name _aip4: #REF!
Name _aip5: #REF!
Name _aip6: #REF!
Name _aip7: #REF!
Name _aip8: #REF!
Name _aip9: #REF!
Name _SH1: #REF!
Name \A: #REF!
Name \blcode1: #REF!
Name \CoefEps: #REF!
Name \CoefSales: #REF!
Name \FactSet_Code: #REF!
Name \FactSet_Code2: #REF!
Name \InputPeriod: #REF!
Name \LastActualPeriod: #REF!
Name \List: #REF!
Name \riccode1: #REF!
Name A: {#N/A,#N/A,FALSE,"Projections";#N/A,#N/A,FALSE,"Multiples Valuation";#N/A,#N/A,FALSE,"LBO";#N/A,#N/A,FALSE,"Multiples_Sensitivity";#N/A,#N/A,FALSE,"Summary"}
Name ABSORB: #REF!
Name ABSORPTION1: #REF!
Name ACC_END_DATE: #REF!
Name ACC_YEAR: #REF!
Name Accounts_payable_and_accrued_expenses: #REF!
Name Accounts_receivable___net: #REF!
Name ACQ_BUS_CF: #REF!
Name ACQ_INV: #REF!
Name AMORT_CF: #REF!
Name AprilActual: #REF!
Name AprilBudget: #REF!
Name AS2HasNoAutoHeaderFooter: "OFF"
Name asdasd: Sheet1
Name ASSETS_CURR: #REF!
Name ASSETS_CURR_OTH: #REF!
Name ASSETS_OTH: #REF!
Name ASSETS_TOT: #REF!
Name asxx: [0]!asxx
Name AugActual: #REF!
Name AugBudget: #REF!
Name BalSheet: #REF!
Name BPS: #REF!
Name bs: #REF!
Name Button2: {"Mcp08.PrintRep",""}

Sheet treatment cost
O1: Annual treatment cost (RMB)
O2: For prostate cancer China/US mkt mono: RMB111K/336K per year; For prostate cancer China mkt combo: RMB225K per year; For breast cancer US/China mkt: RMB420/421K per year.
O3: For AGA China/US mkt: RMB6.5K/8.5K per year; For acne China/US mkt: RMB8.1K/4.0K per year.
O4: For HCC Taiwan/China/US mkts: RMB335K per year.
O5: For prostate cancer/TNBC/HCC treatments: RMB278K per year.
C6: GT0918 | D6: 40mg | E6: For prostate cancer mono treatment China mkt (200mg) | F6: For prostate cancer mono treatment US mkt (400mg) | G6: For prostate cancer combo treatment China mkt (400mg) | H6: 40mg | I6: For breast cancer China mkt (320mg) | J6: 40mg | K6: For breast cancer US mkt (320mg)
D7: Unit Price (from 2021 to 2022, promotion of buy one get one free; NRDL inclusion in 2023 with price cut of 50%) calculate according to 40mg XTANDI | E7: 144 | F7: 222 | G7: 144 | H7: Unit Price | I7: 144 | J7: Unit Price | K7: 222
D8: Dosage | E8: 4.95 | F8: 10 | G8: 10 | H8: Dosage | I8: 8 | J8: Dosage | K8: 8
D9: Duration (China: 8 months, once daily;US: 6 Months once daily) | E9: 224 | F9: 168 | G9: 224 | H9: Duration (12months, once daily) | I9: 360 | J9: Duration (12 months, once daily) | K9: 360
D10: Annual treatment cost (RMB) | E10: =E7*E8*E9 -> 159667.2 | F10: =F7*F8*F9 -> 372960 | G10: =G7*G8*G9 -> 322560 | H10: Annual treatment cost (RMB) | I10: =I7*I8*I9 -> 414720 | J10: Annual treatment cost (RMB) | K10: =K7*K8*K9 -> 639360
C12: KX826 | E12: For AGA China mkt | G12: For AGA US mkt | I12: For acne China mkt | K12: For acne US mkt
D13: Unit Price (proxy: Finasteride,buy 1 get 1 free) | E13: 500 | F13: Unit Price (proxy: Finasteride,buy 1 get 1 free) | G13: 700 | H13: Unit Price (proxy: Yousiming) | I13: 250 | J13: Unit Price (proxy: Yousiming) | K13: 300
D14: Dosage (Tube) | E14: 24 | F14: Dosage (Tube) | G14: 24 | H14: Dosage (Tube) | I14: 2 | J14: Dosage | K14: 2
D15: Duration (12 months, once daily) | E15: - | F15: Duration (12 months, once daily) | G15: - | H15: Duration (12 months) | I15: - | J15: Duration (12 months, once daily) | K15: -
D16: Annual treatment cost (RMB) | E16: =E13*E14/2 -> 6000 | F16: Annual treatment cost (RMB) | G16: =G13*G14/2 -> 8400 | H16: Annual treatment cost (RMB) | I16: =I13*I14 -> 500 | J16: Annual treatment cost (RMB) | K16: =K13*K14 -> 600
C18: GT90001 | D18: 200mg | E18: For HCC (Taiwan, US, China mkts) | G18: GT0486 | H18: 150mg | I18: For prostate cancer, TNBC, HCC
D19: Unit Price (proxy: Nexavar) | E19: 500 | H19: Unit Price (proxy: Lynparza) | I19: 310
D20: Dosage (60k*13.3mg/200mg) | E20: 3.99 | H20: Dosage (60kg*10mg/150mg) | I20: 4
D21: Duration (6 months, daily for 28 days) | E21: 168 | H21: Duration (8 months, twice daily) | I21: 224
D22: Annual treatment cost (RMB) | E22: =E19*E20*E21 -> 335160 | H22: Annual treatment cost (RMB) | I22: =I19*I20*I21 -> 277760
D28: Indication | E28: Market | F28: Annual treatment cost ('000, RMB)
C29: GT0918 | D29: Prostate cancer | E29: China mkt (monotherapy) | F29: =H29/1000 -> 159.6672 | H29: 159667.2
E30: US mkt (monotherapy) | F30: =H30/1000 -> 372.96 | H30: 372960
E31: China mkt (combotherapy) | F31: =H31/1000 -> 322.56 | H31: 322560
D32: Breast cancer | E32: China mkt | F32: =H32/1000 -> 414.72 | H32: 414720
E33: US mkt | F33: =H33/1000 -> 639.36 | H33: 639360
C34: KX826 | D34: AGA | E34: China mkt | F34: =H34/1000 -> 6 | H34: 6000
E35: US mkt | F35: =H35/1000 -> 8.4 | H35: 8400
D36: Acne | E36: China mkt | F36: =H36/1000 -> 0.5 | H36: 500
E37: US mkt | F37: =H37/1000 -> 0.6 | H37: 600
C38: GT90001 | D38: For HCC (Taiwan, US, China mkts) | F38: =H38/1000 -> 335.16 | H38: 335160
C39: GT0486 | D39: For prostate cancer, TNBC, HCC | F39: =H39/1000 -> 277.76 | H39: 277760
C45: Product | D45: Indication | E45: Market | F45: Annual treatment cost ('000, RMB)
C46: GT0918 (Proxalutamide) | D46: Prostate cancer | E46: China (monotherapy) | F46: 159.7
E47: US (monotherapy) | F47: 373
E48: China (combo therapy) | F48: 322.6
D49: Breast cancer | E49: China | F49: 414.7
E50: US | F50: 639.4
C51: KX826 (Pyrilutamide) | D51: AGA | E51: China | F51: 6
E52: US | F52: 8.4
D53: Acne | E53: China | F53: 0.5
E54: US | F54: 0.6
C55: GT90001 (ALK-1) | D55: HCC | E55: Taiwan, US, China | F55: 335.2
C56: GT0486 (Detorsertib) | D56: Prostate cancer, TNBC, HCC | E56: China | F56: 277.8
C62: Product | D62: Indication
C63: GT0918 (Proxalutamide) | D63: Prostate cancer
D64: Breast cancer
C65: KX826 (Pyrilutamide) | D65: AGA
D66: Acne
C67: GT90001 (ALK-1) | D67: HCC
C68: GT0486 (Detorsertib) | D68: Prostate cancer, TNBC, HCC

Sheet Portfolio Guide
B2: Healthcare Equity Research & Financial Modeling
B5: Selected modeling work adapted for portfolio presentation. The workbook preserves the original modeling structure (DCF, integrated financial statements, pipeline forecasts, and financial analysis) while removing employer attribution.
B8: START HERE — WHAT TO LOOK AT
B10: Tab | C10: What it demonstrates | D10: Best portfolio use
B11: Financial Analysis | C11: Revenue, gross profit, net income and operating trend exhibits. | D11: Visual proof of financial analysis and presentation.
B12: DCF | C12: Free cash flow build, WACC, terminal value, equity value and sensitivity analysis. | D12: Core valuation/modeling project.
B13: ISBSCF | C13: Integrated Income Statement, Balance Sheet and Cash Flow forecast. | D13: Three-statement modeling capability.
B14: Summary | C14: Pipeline-level revenue, gross profit, treated-patient and peak-sales outputs. | D14: Healthcare forecasting methodology.
B15: APL101 / APL121 / APL106 / APL501 | C15: Product-level patient, penetration, pricing and revenue build. | D15: Detailed pharmaceutical pipeline modeling.
B16: Forecast | C16: Operating assumptions and forecast drivers feeding the financial statements. | D16: Shows model linkage and forecasting logic.
B17: Key Financial Ratios | C17: Selected profitability, liquidity and operating ratios. | D17: Supporting analytical output.
B20: PORTFOLIO DESCRIPTION
B22: Built and analyzed a healthcare equity-research model incorporating product-level revenue forecasting, integrated financial statements, free-cash-flow valuation, WACC and terminal-value assumptions, sensitivity analysis, and financial-performance exhibits. The model links patient/population assumptions and product forecasts to company-level financial statements and valuation outputs.
B28: PUBLIC-SHARING NOTE
B30: This portfolio copy is intended to demonstrate modeling methodology. Employer attribution has been removed. Before publishing the workbook publicly, confirm that the underlying company/model data and template are permitted to be shared; otherwise use screenshots or a further anonymized recreation on the website.

Sheet Financial Analysis
A1: Portfolio copy — employer attribution removed; modeling structure preserved.
A2: Exhibit 28: Illustrative Biotech Co. 2020E-40E revenue (RMB mn)
B4: 2020E | C4: 2021E | D4: 2022E | E4: 2023E | F4: 2024E | G4: 2025E | H4: 2026E | I4: 2027E | J4: 2028E | K4: 2029E | L4: 2030E | M4: 2031E | N4: 2032E | O4: 2033E | P4: 2034E | Q4: 2035E | R4: 2036E | S4: 2037E | T4: 2038E | U4: 2039E | V4: 2040E
A5: APL101 | B5: =Summary!H8 -> 0 | C5: =Summary!I8 -> 0 | D5: =Summary!J8 -> 0 | E5: =Summary!K8 -> 0 | F5: =Summary!L8 -> 30.668977 | G5: =Summary!M8 -> 94.391777 | H5: =Summary!N8 -> 161.45759 | I5: =Summary!O8 -> 232.06927 | ... V5: =Summary!AB8 -> 179.73081
A6: APL121 | B6: =Summary!H9 -> #REF! | C6: =Summary!I9 -> #REF! | D6: =Summary!J9 -> #REF! | E6: =Summary!K9 -> #REF! | F6: =Summary!L9 -> #REF! | G6: =Summary!M9 -> #REF! | H6: =Summary!N9 -> #REF! | I6: =Summary!O9 -> #REF! | ... V6: =Summary!AB9 -> #REF!
A7: APL106 | B7: =Summary!H10 -> #REF! | C7: =Summary!I10 -> #REF! | D7: =Summary!J10 -> #REF! | E7: =Summary!K10 -> #REF! | F7: =Summary!L10 -> #REF! | G7: =Summary!M10 -> #REF! | H7: =Summary!N10 -> #REF! | I7: =Summary!O10 -> #REF! | ... V7: =Summary!AB10 -> #REF!
A8: APL501 | B8: =Summary!H11 -> #REF! | C8: =Summary!I11 -> #REF! | D8: =Summary!J11 -> #REF! | E8: =Summary!K11 -> #REF! | F8: =Summary!L11 -> #REF! | G8: =Summary!M11 -> #REF! | H8: =Summary!N11 -> #REF! | I8: =Summary!O11 -> #REF! | ... V8: =Summary!AB11 -> #REF!
A32: Exhibit 29: Illustrative Biotech Co. revenue (RMB mn)
B33: 2019E | C33: 2020E | D33: 2021E | E33: 2022E | F33: 2023E | G33: 2024E | H33: 2025E | I33: 2026E | J33: 2027E | K33: 2028E | L33: 2029E | M33: 2030E
A34: Revenue (LHS) | B34: =ISBSCF!D6 -> 0 | C34: =ISBSCF!E6 -> #REF! | D34: =ISBSCF!F6 -> #REF! | E34: =ISBSCF!G6 -> #REF! | F34: =ISBSCF!H6 -> #REF! | G34: =ISBSCF!I6 -> #REF! | H34: =ISBSCF!J6 -> #REF! | I34: =ISBSCF!K6 -> #REF! | ... M34: =ISBSCF!O6 -> #REF!
A35: Revenue YoY (RHS) | E35: =E34/D34-1 -> #REF! | F35: =F34/E34-1 -> #REF! | G35: =G34/F34-1 -> #REF! | H35: =H34/G34-1 -> #REF! | I35: =I34/H34-1 -> #REF! | J35: =J34/I34-1 -> #REF! | K35: =K34/J34-1 -> #REF! | L35: =L34/K34-1 -> #REF! | M35: =M34/L34-1 -> #REF!
A55: Exhibit 30: Apollomics’s gross profit (RMB mn)
B56: 2019 | C56: 2020E | D56: 2021E | E56: 2022E | F56: 2023E | G56: 2024E | H56: 2025E | I56: 2026E | J56: 2027E | K56: 2028E | L56: 2029E | M56: 2030E
A57: Gross profit (LHS) | B57: =ISBSCF!D8 -> 0 | C57: =ISBSCF!E8 -> #REF! | D57: =ISBSCF!F8 -> #REF! | E57: =ISBSCF!G8 -> #REF! | F57: =ISBSCF!H8 -> #REF! | G57: =ISBSCF!I8 -> #REF! | H57: =ISBSCF!J8 -> #REF! | I57: =ISBSCF!K8 -> #REF! | ... M57: =ISBSCF!O8 -> #REF!
A58: Gross profit YoY (RHS) | E58: =E57/D57-1 -> #REF! | F58: =F57/E57-1 -> #REF! | G58: =G57/F57-1 -> #REF! | H58: =H57/G57-1 -> #REF! | I58: =I57/H57-1 -> #REF! | J58: =J57/I57-1 -> #REF! | K58: =K57/J57-1 -> #REF! | L58: =L57/K57-1 -> #REF! | M58: =M57/L57-1 -> #REF!
A76: Exhibit 30: Apollomics’s net income (RMB mn)
B77: 2019 | C77: 2020E | D77: 2021E | E77: 2022E | F77: 2023E | G77: 2024E | H77: 2025E | I77: 2026E | J77: 2027E | K77: 2028E | L77: 2029E | M77: 2030E
A78: Net income to common shareholders (LHS) | B78: =ISBSCF!D25 -> -45.905 | C78: =ISBSCF!E25 -> #REF! | D78: =ISBSCF!F25 -> #REF! | E78: =ISBSCF!G25 -> #REF! | F78: =ISBSCF!H25 -> #REF! | G78: =ISBSCF!I25 -> #REF! | H78: =ISBSCF!J25 -> #REF! | I78: =ISBSCF!K25 -> #REF! | ... M78: =ISBSCF!O25 -> #REF!
A79: Net income YoY (RHS) | C79: =IFERROR(-(C78/B78-1),"NM") -> NM | D79: =IFERROR(-(D78/C78-1),"NM") -> NM | E79: =IFERROR(-(E78/D78-1),"NM") -> NM | F79: =IFERROR(-(F78/E78-1),"NM") -> NM | G79: =IFERROR(-(G78/F78-1),"NM") -> NM | H79: =IFERROR(-(H78/G78-1),"NM") -> NM | I79: =I78/H78-1 -> #REF! | J79: =J78/I78-1 -> #REF! | K79: =K78/J78-1 -> #REF! | L79: =L78/K78-1 -> #REF! | M79: =M78/L78-1 -> #REF!
A84: Exhibit 31: Apollomics’s GPM and NPM
B85: 2019E | C85: 2020E | D85: 2021E | E85: 2022E | F85: 2023E | G85: 2024E | H85: 2025E | I85: 2026E | J85: 2027E | K85: 2028E | L85: 2029E | M85: 2030E
A86: Gross profit | B86: =B57 -> 0 | C86: =C57 -> #REF! | D86: =D57 -> #REF! | E86: =E57 -> #REF! | F86: =F57 -> #REF! | G86: =G57 -> #REF! | H86: =H57 -> #REF! | I86: =I57 -> #REF! | ... M86: =M57 -> #REF!
A87: Net profit | B87: =ISBSCF!D25 -> -45.905 | C87: =ISBSCF!E25 -> #REF! | D87: =ISBSCF!F25 -> #REF! | E87: =ISBSCF!G25 -> #REF! | F87: =ISBSCF!H25 -> #REF! | G87: =ISBSCF!I25 -> #REF! | H87: =ISBSCF!J25 -> #REF! | I87: =ISBSCF!K25 -> #REF! | ... M87: =ISBSCF!O25 -> #REF!
A88: GPM | B88: =B86/ISBSCF!D6 -> #DIV/0! | C88: =C86/ISBSCF!E6 -> #REF! | D88: =D86/ISBSCF!F6 -> #REF! | E88: =E86/ISBSCF!G6 -> #REF! | F88: =F86/ISBSCF!H6 -> #REF! | G88: =G86/ISBSCF!I6 -> #REF! | H88: =H86/ISBSCF!J6 -> #REF! | I88: =I86/ISBSCF!K6 -> #REF! | ... M88: =M86/ISBSCF!O6 -> #REF!
A89: NPM | B89: =B87/ISBSCF!D6 -> #DIV/0! | C89: =C87/ISBSCF!E6 -> #REF! | D89: =D87/ISBSCF!F6 -> #REF! | E89: =E87/ISBSCF!G6 -> #REF! | F89: =F87/ISBSCF!H6 -> #REF! | G89: =G87/ISBSCF!I6 -> #REF! | H89: =H87/ISBSCF!J6 -> #REF! | I89: =I87/ISBSCF!K6 -> #REF! | ... M89: =M87/ISBSCF!O6 -> #REF!
A108: Exhibit 32: Apollomics’s FCF trend (US$ mn)
B109: 2018 | C109: 2019 | D109: 2020E | E109: 2021E | F109: 2022E | G109: 2023E | H109: 2024E | I109: 2025E | J109: 2026E | K109: 2027E | L109: 2028E
A110: FCF | B110: =DCF!G14 -> 0 | C110: =DCF!H14 -> -45.047 | D110: =DCF!I14 -> #REF! | E110: =DCF!J14 -> #REF! | F110: =DCF!K14 -> #REF! | G110: =DCF!L14 -> #REF! | H110: =DCF!M14 -> #REF! | I110: =DCF!N14 -> #REF! | ... L110: =DCF!Q14 -> #REF!
A131: Exhibit 33: Apollomics’s cash expenses (US$ mn)
B132: 2020E | C132: 2021E | D132: 2022E | E132: 2023E
A133: R&D expenses | B133: =-ISBSCF!E11 -> 27.663 | C133: =-ISBSCF!F11 -> 41.4945 | D133: =-ISBSCF!G11 -> 58.0923 | E133: =-ISBSCF!H11 -> 81.32922 | F133: =-ISBSCF!I11 -> 113.86091
A134: Selling expense | B134: =-ISBSCF!E13 -> 0 | C134: =-ISBSCF!F13 -> #REF! | D134: =-ISBSCF!G13 -> #REF! | E134: =-ISBSCF!H13 -> #REF! | F134: =-ISBSCF!I13 -> #REF!
A135: Admin expense | B135: =-ISBSCF!E12 -> 9.459 | C135: =-ISBSCF!F12 -> 14.1885 | D135: =-ISBSCF!G12 -> 21.28275 | E135: =-ISBSCF!H12 -> 31.924125 | F135: =-ISBSCF!I12 -> 47.886187
A136: Cap Ex | B136: =-DCF!I13 -> 10.313 | C136: =-DCF!J13 -> 10.357 | D136: =-DCF!K13 -> 10.357 | E136: =-DCF!L13 -> 10.357 | F136: =-DCF!M13 -> 10.357
B150: Product | C150: Expected launch year | D150: Peak sales (US$ mn) | E150: Peak # of patients treated （000s） | F150: Year of peak sales | G150: Annual treatment cost (RMB)
B151: APL101 | C151: =Summary!I35 -> 2024 | D151: =Summary!G35 -> 324.55917 | E151: =Summary!G44 -> 16.402055 | F151: =Summary!K35 -> 2029
B152: APL121 | C152: =Summary!I36 -> 2026 | D152: =Summary!G36 -> #REF! | E152: =Summary!G45 -> #REF! | F152: =Summary!K36 -> 2032 | G152: For AGA China/US mkt: RMB6.5K/8.5K per year; For acne China/US mkt: RMB8.1K/4.0K per year.
B153: APL106 | C153: =Summary!I37 -> 2024 | D153: =Summary!G37 -> #REF! | E153: =Summary!G46 -> #REF! | F153: =Summary!K37 -> 2030 | G153: For HCC Taiwan/China/US mkts: RMB335K per year.
B154: APL501 | C154: =Summary!I38 -> 2025 | D154: =Summary!G38 -> #REF! | E154: =Summary!G47 -> #REF! | F154: =Summary!K38 -> 2030 | G154: For prostate cancer China/US mkt mono: RMB111K/336K per year; For prostate cancer China mkt combo: RMB225K per year; For breast cancer US/China mkt: RMB420/421K per year.
C182: 2019 | D182: 9M20
B183: R&D Third-Party Service Fees | C183: 12.681 | D183: 16.462
B184: R&D Employee Compensations and Benefits | C184: 4.259 | D184: 4.638
B185: R&D Contractor Expenses | C185: 1.502 | D185: 0.971
B186: Total | C186: =SUM(C183:C185) -> 18.442 | D186: =SUM(D183:D185) -> 22.071
B187: YoY | D187: =D186/C186-1 -> 0.19677909
H198: Product | I198: Indication | J198: Annual treatment cost ('000, RMB)
H199: APL101 | I199: Non-small cell lung cancer (NSCLC) | J199: 90.06624
I200: Renal cell carcinoma (RCC) | J200: 90.06624
I201: Glioblastoma | J201: 90.06624
H202: APL121 | I202: Non-small cell lung cancer (NSCLC) | J202: 378.04
I203: Acute myeloid leukemia (AML)
H204: APL106 | I204: Acute myeloid leukemia (AML) | J204: 119.448
H205: APL501 | I205: Non-small cell lung cancer (NSCLC) | J205: 221.37143
I206: Colerectal Cancer (CRC) | J206: 366.6988
I207: Hepatocellular carcinoma
I208: PMBCL
I209: PTCL
I210: Cervical Cancer
I211: ASPS Sarcoma
L212: 1000

Sheet Summary
A1: Portfolio copy — employer attribution removed; modeling structure preserved.
F5: Year | G5: 2019 | H5: =G5+1 -> 2020 | I5: =H5+1 -> 2021 | J5: =I5+1 -> 2022 | K5: =J5+1 -> 2023 | L5: =K5+1 -> 2024 | M5: =L5+1 -> 2025 | N5: =M5+1 -> 2026 | O5: =N5+1 -> 2027 | ... AB5: =AA5+1 -> 2040
F6: T = | G6: 0 | H6: 1 | I6: 2 | J6: 3 | K6: 4 | L6: 5 | M6: 6 | N6: 7 | O6: 8 | P6: 9 | Q6: 10 | R6: 11 | S6: 12 | T6: 13 | U6: 14 | V6: 15 | W6: 16 | X6: 17 | Y6: 18 | Z6: 19 | AA6: 20 | AB6: 21
F7: Expected revenue (US$ mn)
F8: APL101 | G8: ='APL101'!P135 -> 0 | H8: ='APL101'!Q135 -> 0 | I8: ='APL101'!R135 -> 0 | J8: ='APL101'!S135 -> 0 | K8: ='APL101'!T135 -> 0 | L8: ='APL101'!U135 -> 30.668977 | M8: ='APL101'!V135 -> 94.391777 | N8: ='APL101'!W135 -> 161.45759 | ... AB8: ='APL101'!AK135 -> 179.73081
F9: APL121 | G9: =#REF! -> #REF! | H9: =#REF! -> #REF! | I9: =#REF! -> #REF! | J9: =#REF! -> #REF! | K9: =#REF! -> #REF! | L9: =#REF! -> #REF! | M9: =#REF! -> #REF! | N9: =#REF! -> #REF! | ... AB9: =#REF! -> #REF!
F10: APL106 | G10: =#REF! -> #REF! | H10: =#REF! -> #REF! | I10: =#REF! -> #REF! | J10: =#REF! -> #REF! | K10: =#REF! -> #REF! | L10: =#REF! -> #REF! | M10: =#REF! -> #REF! | N10: =#REF! -> #REF! | ... AB10: =#REF! -> #REF!
F11: APL501 | G11: =#REF! -> #REF! | H11: =#REF! -> #REF! | I11: =#REF! -> #REF! | J11: =#REF! -> #REF! | K11: =#REF! -> #REF! | L11: =#REF! -> #REF! | M11: =#REF! -> #REF! | N11: =#REF! -> #REF! | ... AB11: =#REF! -> #REF!
F12: Total | G12: =SUM(G8:G11) -> #REF! | H12: =SUM(H8:H11) -> #REF! | I12: =SUM(I8:I11) -> #REF! | J12: =SUM(J8:J11) -> #REF! | K12: =SUM(K8:K11) -> #REF! | L12: =SUM(L8:L11) -> #REF! | M12: =SUM(M8:M11) -> #REF! | N12: =SUM(N8:N11) -> #REF! | ... AB12: =SUM(AB8:AB11) -> #REF!
F17: Expected gross profit (US$ mn)
F18: APL101 | G18: =G8*0.9 -> 0 | H18: =H8*0.9 -> 0 | I18: =I8*0.9 -> 0 | J18: =J8*0.9 -> 0 | K18: =K8*0.9 -> 0 | L18: =L8*0.9 -> 27.602079 | M18: =M8*0.9 -> 84.952599 | N18: =N8*0.9 -> 145.31183 | ... AB18: =AB8*0.9 -> 161.75773
F19: APL121 | G19: =G9*0.9 -> #REF! | H19: =H9*0.9 -> #REF! | I19: =I9*0.9 -> #REF! | J19: =J9*0.9 -> #REF! | K19: =K9*0.9 -> #REF! | L19: =L9*0.9 -> #REF! | M19: =M9*0.9 -> #REF! | N19: =N9*0.9 -> #REF! | ... AB19: =AB9*0.9 -> #REF!
F20: APL106 | G20: =G10*0.9 -> #REF! | H20: =H10*0.9 -> #REF! | I20: =I10*0.9 -> #REF! | J20: =J10*0.9 -> #REF! | K20: =K10*0.9 -> #REF! | L20: =L10*0.9 -> #REF! | M20: =M10*0.9 -> #REF! | N20: =N10*0.9 -> #REF! | ... AB20: =AB10*0.9 -> #REF!
F21: APL501 | G21: =G11*0.9 -> #REF! | H21: =H11*0.9 -> #REF! | I21: =I11*0.9 -> #REF! | J21: =J11*0.9 -> #REF! | K21: =K11*0.9 -> #REF! | L21: =L11*0.9 -> #REF! | M21: =M11*0.9 -> #REF! | N21: =N11*0.9 -> #REF! | ... AB21: =AB11*0.9 -> #REF!
F22: Total | G22: =SUM(G18:G21) -> #REF! | H22: =SUM(H18:H21) -> #REF! | I22: =SUM(I18:I21) -> #REF! | J22: =SUM(J18:J21) -> #REF! | K22: =SUM(K18:K21) -> #REF! | L22: =SUM(L18:L21) -> #REF! | M22: =SUM(M18:M21) -> #REF! | N22: =SUM(N18:N21) -> #REF! | ... AB22: =SUM(AB18:AB21) -> #REF!
F24: # of patients treated ('000)
F25: APL101 | G25: ='APL101'!P137 -> 0 | H25: ='APL101'!Q137 -> 0 | I25: ='APL101'!R137 -> 0 | J25: ='APL101'!S137 -> 0 | K25: ='APL101'!T137 -> 0 | L25: ='APL101'!U137 -> 0.69979698 | M25: ='APL101'!V137 -> 2.2204203 | N25: ='APL101'!W137 -> 3.9155049 | ... AB25: ='APL101'!AK137 -> 16.402055
F26: APL121 | G26: =#REF! -> #REF! | H26: =#REF! -> #REF! | I26: =#REF! -> #REF! | J26: =#REF! -> #REF! | K26: =#REF! -> #REF! | L26: =#REF! -> #REF! | M26: =#REF! -> #REF! | N26: =#REF! -> #REF! | ... AB26: =#REF! -> #REF!
F27: APL106 | G27: =#REF! -> #REF! | H27: =#REF! -> #REF! | I27: =#REF! -> #REF! | J27: =#REF! -> #REF! | K27: =#REF! -> #REF! | L27: =#REF! -> #REF! | M27: =#REF! -> #REF! | N27: =#REF! -> #REF! | ... AB27: =#REF! -> #REF!
F28: APL501 | G28: =#REF! -> #REF! | H28: =#REF! -> #REF! | I28: =#REF! -> #REF! | J28: =#REF! -> #REF! | K28: =#REF! -> #REF! | L28: =#REF! -> #REF! | M28: =#REF! -> #REF! | N28: =#REF! -> #REF! | ... AB28: =#REF! -> #REF!
F34: Peak sales (US$ mn) | I34: Expected launch year | K34: Year of peak sales
F35: APL101 | G35: =MAX(G8:AB8) -> 324.55917 | I35: 2024 | K35: 2029
F36: APL121 | G36: =MAX(G9:AB9) -> #REF! | I36: 2026 | K36: 2032
F37: APL106 | G37: =MAX(G10:AB10) -> #REF! | I37: 2024 | K37: 2030
F38: APL501 | G38: =MAX(G11:AB11) -> #REF! | I38: 2025 | K38: 2030
F43: Peak # of patients treated ('000)
F44: APL101 | G44: =MAX(G25:AB25) -> 16.402055
F45: APL121 | G45: =MAX(G26:AB26) -> #REF!
F46: APL106 | G46: =MAX(G27:AB27) -> #REF!
F47: APL501 | G47: =MAX(G28:AB28) -> #REF!
F50: Royalty fees (US$ mn)
F51: APL121 | G51: =#REF! -> #REF! | H51: =#REF! -> #REF! | I51: =#REF! -> #REF! | J51: =#REF! -> #REF! | K51: =#REF! -> #REF! | L51: =#REF! -> #REF! | M51: =#REF! -> #REF! | N51: =#REF! -> #REF! | ... AB51: =#REF! -> #REF!
F52: APL106 | G52: =#REF! -> #REF! | H52: =#REF! -> #REF! | I52: =#REF! -> #REF! | J52: =#REF! -> #REF! | K52: =#REF! -> #REF! | L52: =#REF! -> #REF! | M52: =#REF! -> #REF! | N52: =#REF! -> #REF! | ... AB52: =#REF! -> #REF!

Sheet DCF
A1: Portfolio copy — employer attribution removed; modeling structure preserved.
F5: US$ mn | H5: 2019A | I5: 2020E | J5: 2021E | K5: 2022E | L5: 2023E | M5: 2024E | N5: 2025E | O5: 2026E | P5: 2027E | Q5: 2028E
F6: Profit before tax | H6: =ISBSCF!D22 -> -45.752 | I6: =ISBSCF!E22 -> #REF! | J6: =ISBSCF!F22 -> #REF! | K6: =ISBSCF!G22 -> #REF! | L6: =ISBSCF!H22 -> #REF! | M6: =ISBSCF!I22 -> #REF! | N6: =ISBSCF!J22 -> #REF! | O6: =ISBSCF!K22 -> #REF! | ... Q6: =ISBSCF!M22 -> #REF!
F7: Finance costs | H7: =-ISBSCF!D21 -> 0.046 | I7: =-ISBSCF!E21 -> -0.76974 | J7: =-ISBSCF!F21 -> #REF! | K7: =-ISBSCF!G21 -> #REF! | L7: =-ISBSCF!H21 -> #REF! | M7: =-ISBSCF!I21 -> #REF! | N7: =-ISBSCF!J21 -> #REF! | O7: =-ISBSCF!K21 -> #REF! | ... Q7: =-ISBSCF!M21 -> #REF!
F8: EBIT | H8: =H6+H7 -> -45.706 | I8: =I6+I7 -> #REF! | J8: =J6+J7 -> #REF! | K8: =K6+K7 -> #REF! | L8: =L6+L7 -> #REF! | M8: =M6+M7 -> #REF! | N8: =N6+N7 -> #REF! | O8: =O6+O7 -> #REF! | ... Q8: =Q6+Q7 -> #REF!
F9: EBIT*(1-t) | H9: =H8+ISBSCF!D23 -> -45.859 | I9: =I8+ISBSCF!E23 -> #REF! | J9: =J8+ISBSCF!F23 -> #REF! | K9: =K8+ISBSCF!G23 -> #REF! | L9: =L8+ISBSCF!H23 -> #REF! | M9: =M8+ISBSCF!I23 -> #REF! | N9: =N8+ISBSCF!J23 -> #REF! | O9: =O8+ISBSCF!K23 -> #REF! | ... Q9: =Q8+ISBSCF!M23 -> #REF!
F10: Depreciation of PP&E | H10: =ISBSCF!D73 -> 0.039 | I10: =ISBSCF!E73 -> 0.039 | J10: =ISBSCF!F73 -> 0.039 | K10: =ISBSCF!G73 -> 0.039 | L10: =ISBSCF!H73 -> 0.039 | M10: =ISBSCF!I73 -> 0.039 | N10: =ISBSCF!J73 -> 0.039 | O10: =ISBSCF!K73 -> 0.039 | ... Q10: =ISBSCF!M73 -> 0.039
F11: Amortization of intangible assets | H11: =ISBSCF!D75 -> 0.02 | I11: =ISBSCF!E75 -> 1 | J11: =ISBSCF!F75 -> 1 | K11: =ISBSCF!G75 -> 1 | L11: =ISBSCF!H75 -> 1 | M11: =ISBSCF!I75 -> 1 | N11: =ISBSCF!J75 -> 1 | O11: =ISBSCF!K75 -> 1 | ... Q11: =ISBSCF!M75 -> 1
F12: Net change in WC | H12: =ISBSCF!D84 -> 1.11 | I12: =ISBSCF!E84 -> #REF! | J12: =ISBSCF!F84 -> #REF! | K12: =ISBSCF!G84 -> #REF! | L12: =ISBSCF!H84 -> #REF! | M12: =ISBSCF!I84 -> #REF! | N12: =ISBSCF!J84 -> #REF! | O12: =ISBSCF!K84 -> #REF! | ... Q12: =ISBSCF!M84 -> #REF!
F13: CapEx | H13: =ISBSCF!D96 -> -0.357 | I13: =ISBSCF!E96+ISBSCF!E97 -> -10.313 | J13: =ISBSCF!F96+ISBSCF!F97 -> -10.357 | K13: =ISBSCF!G96+ISBSCF!G97 -> -10.357 | L13: =ISBSCF!H96+ISBSCF!H97 -> -10.357 | M13: =ISBSCF!I96+ISBSCF!I97 -> -10.357 | N13: =ISBSCF!J96+ISBSCF!J97 -> -10.357 | O13: =ISBSCF!K96+ISBSCF!K97 -> -10.357 | P13: =ISBSCF!L96+ISBSCF!L97 -> -10.357 | Q13: =ISBSCF!M96+ISBSCF!M97 -> -10.357
F14: FCF | H14: =SUM(H9:H13) -> -45.047 | I14: =SUM(I9:I13) -> #REF! | J14: =SUM(J9:J13) -> #REF! | K14: =SUM(K9:K13) -> #REF! | L14: =SUM(L9:L13) -> #REF! | M14: =SUM(M9:M13) -> #REF! | N14: =SUM(N9:N13) -> #REF! | O14: =SUM(O9:O13) -> #REF! | ... Q14: =SUM(Q9:Q13) -> #REF!
F15: Discount factor | I15: 0 | J15: 0 | K15: 1 | L15: 2 | M15: 3 | N15: 4 | O15: 5 | P15: 6 | Q15: 7
F16: PV of FCF | H16: =H14/(1+$J$27)^H15 -> #REF! | I16: =I14/(1+$J$27)^I15 -> #REF! | J16: =J14/(1+$J$27)^J15 -> #REF! | K16: =K14/(1+$J$27)^K15 -> #REF! | L16: =L14/(1+$J$27)^L15 -> #REF! | M16: =M14/(1+$J$27)^M15 -> #REF! | N16: =N14/(1+$J$27)^N15 -> #REF! | O16: =O14/(1+$J$27)^O15 -> #REF! | ... Q16: =Q14/(1+$J$27)^Q15 -> #REF!
F18: Valuation summary | G18: as of 2021 YE | I18: WACC derivation | L18: Equity Value sensitivity analysis on terminal growth rate (line) and WACC (row)
F19: PV of DCF (2021E-2028E) | G19: =SUM(J16:Q16) -> #REF! | I19: Risk-free rate | J19: 0.03 | L19: =G24 -> #REF! | M19: =N19-0.15% -> 0.087 | N19: =O19-0.15% -> 0.0885 | O19: 0.09 | P19: =O19+0.15% -> 0.0915 | Q19: =P19+0.15% -> 0.093
F20: PV of terminal value (Tg =3.0%) | G20: =Q14*(1+J29)/(J27-J29)/((1+J27)^Q15) -> #REF! | I20: Equity risk premium | J20: 0.06 | L20: =L21-0.15% -> 0.027 | M20: #REF! | N20: #REF! | O20: #REF! | P20: #REF! | Q20: #REF!
F21: Total enterprise value | G21: =SUM(G19:G20) -> #REF! | I21: Beta | J21: 1 | L21: =L22-0.15% -> 0.0285 | M21: #REF! | N21: #REF! | O21: #REF! | P21: #REF! | Q21: #REF!
F22: ( -）Net debt | G22: 0 | I22: Cost of equity | J22: =J19+J20*J21 -> 0.09 | L22: 0.03 | M22: #REF! | N22: #REF! | O22: #REF! | P22: #REF! | Q22: #REF!
F23: ( -）Minority interests | G23: 0 | I23: Cost of debt | J23: 0.05 | L23: =L22+0.15% -> 0.0315 | M23: #REF! | N23: #REF! | O23: #REF! | P23: #REF! | Q23: #REF!
F24: Equity value (US$ mn) | G24: =G21-G22-G23 -> #REF! | I24: Marginal tax rate | J24: 0.25 | L24: =L23+0.15% -> 0.033 | M24: #REF! | N24: #REF! | O24: #REF! | P24: #REF! | Q24: #REF!
F25: Equity value (HK$ mn) | G25: =G24*7.7666 -> #REF! | I25: After tax cost of debt | J25: =J23*(1-J24) -> 0.0375
F26: Shares outstanding (mn) | G26: =ISBSCF!F27 -> 326.03333 | I26: Debt / total capital | J26: =0/(0+ISBSCF!E62) -> #REF!
F27: Target price (HK$) | G27: =G25/G26 -> #REF! | I27: WACC | J27: =J22*(1-J26)+J25*J26 -> #REF! | V27: Low-end | W27: Base case | X27: High-end
F28: Current stock price | U28: post-money | V28: =V35 -> #REF! | W28: =W35 -> #REF! | X28: =X35 -> #REF!
F29: upside/(downside) % | G29: =G27/G28-1 -> #REF! | I29: Terminal growth rate | J29: 0.03 | U29: pre-money | V29: =(V34-3500)/7 -> #REF! | W29: =(W34-3500)/7 -> #REF! | X29: =(X34-3500)/7 -> #REF!
R30: =V35/Summary!$R$12 -> #REF! | S30: =W35/Summary!$R$12 -> #REF! | T30: =X35/Summary!$R$12 -> #REF!
U32: DCF-based valuation range (2020E) | V32: Low-end | W32: Base case | X32: High-end
U33: Equity value (RMB mn) | V33: =V35*6.8 -> #REF! | W33: =W35*6.8 -> #REF! | X33: =X35*6.8 -> #REF!
M34: EV/sales | U34: Equity value (HK$ mn) | V34: =V35*7.7666 -> #REF! | W34: =W35*7.7666 -> #REF! | X34: =X35*7.7666 -> #REF!
M35: 2021 | N35: =(V33-ISBSCF!#REF!)/ISBSCF!F6 -> #REF! | O35: =(W33-ISBSCF!#REF!)/ISBSCF!F6 -> #REF! | P35: =(X33-ISBSCF!#REF!)/ISBSCF!F6 -> #REF! | U35: Equity value (US$ mn) | V35: =P21 -> #REF! | W35: =G24 -> #REF! | X35: =N23 -> #REF!
M36: 2022 | N36: =(V33-ISBSCF!#REF!)/ISBSCF!G6 -> #REF! | O36: =(W33-ISBSCF!#REF!)/ISBSCF!G6 -> #REF! | P36: =(X33-ISBSCF!#REF!)/ISBSCF!G6 -> #REF!
M37: 2025 | N37: =(V33-ISBSCF!#REF!)/ISBSCF!J6 -> #REF! | O37: =(W33-ISBSCF!#REF!)/ISBSCF!K6 -> #REF! | P37: =(X33-ISBSCF!#REF!)/ISBSCF!L6 -> #REF! | U37: WACC | V37: =N19 -> 0.0885 | W37: =O19 -> 0.09 | X37: =P19 -> 0.0915
U38: Terminal growth rate | V38: =L21 -> 0.0285 | W38: =L22 -> 0.03 | X38: =L23 -> 0.0315
U40: Implied 2021E PS ratio | V40: =V33/ISBSCF!F6 -> #REF! | W40: =W33/ISBSCF!F6 -> #REF! | X40: =X33/ISBSCF!F6 -> #REF!
U41: Implied 2022E EV/Sales ratio | V41: =(V33-ISBSCF!#REF!)/ISBSCF!G6 -> #REF! | W41: =(W33-ISBSCF!#REF!)/ISBSCF!G6 -> #REF! | X41: =(X33-ISBSCF!#REF!)/ISBSCF!G6 -> #REF!
L43: 5650 | N43: =V35/$L$43 -> #REF! | O43: =W35/$L$43 -> #REF! | P43: =X35/$L$43 -> #REF!
L44: 2415 | N44: =V35/$L$44 -> #REF! | O44: =W35/$L$44 -> #REF! | P44: =X35/$L$44 -> #REF! | U44: Note: Assume HKD:RMB exchange rate of 1.11; and RMB:USD exchange rate of 7

Sheet ISBSCF
A1: Portfolio copy — employer attribution removed; modeling structure preserved. | L1: =POWER(L6/J6,1/2)-1 -> #REF!
L2: =POWER(L25/J25,1/2)-1 -> #REF!
B3: in US$ mn | C3: 1 | G3: =G6/F6-1 -> #REF! | L3: Breakeven
B4: 利润表(ORIG,百万元)
B5: 3 | C5: Income Statement (US$ mn) | D5: 2019 | E5: 2020 | F5: 2021 | G5: 2022 | H5: 2023 | I5: 2024 | J5: 2025 | K5: 2026 | L5: 2027 | M5: 2028 | N5: 2029 | O5: 2030 | P5: 2031 | Q5: 2032 | R5: 2033 | S5: 2034 | T5: 2035 | U5: 2036 | V5: 2037 | W5: 2038 | X5: 2039 | Y5: 2040
A6: link | B6: 营业收入 | C6: Revenue | D6: 0 | E6: =SUM(Summary!H8:H11) -> #REF! | F6: =SUM(Summary!I8:I11) -> #REF! | G6: =SUM(Summary!J8:J11) -> #REF! | H6: =SUM(Summary!K8:K11) -> #REF! | I6: =SUM(Summary!L8:L11) -> #REF! | J6: =SUM(Summary!M8:M11) -> #REF! | K6: =SUM(Summary!N8:N11) -> #REF! | L6: =SUM(Summary!O8:O11) -> #REF! | ... Y6: =SUM(Summary!AB8:AB11) -> #REF!
B7: 营业成本 | C7: Cost of sales | D7: 0 | E7: =-(E6-E8) -> #REF! | F7: =-(F6-F8) -> #REF! | G7: =-(G6-G8) -> #REF! | H7: =-(H6-H8) -> #REF! | I7: =-(I6-I8) -> #REF! | J7: =-(J6-J8) -> #REF! | K7: =-(K6-K8) -> #REF! | L7: =-(L6-L8) -> #REF! | ... Y7: =-(Y6-Y8) -> #REF!
A8: link | B8: 毛利 | C8: Gross profit | D8: =D6+D7 -> 0 | E8: =Summary!H22 -> #REF! | F8: =Summary!I22 -> #REF! | G8: =Summary!J22 -> #REF! | H8: =Summary!K22 -> #REF! | I8: =Summary!L22 -> #REF! | J8: =Summary!M22 -> #REF! | K8: =Summary!N22 -> #REF! | L8: =Summary!O22 -> #REF! | ... Y8: =Summary!AB22 -> #REF!
B9: 其他收益 | C9: Other income | D9: 1.156 | E9: =D9 -> 1.156 | F9: =E9 -> 1.156 | G9: =F9 -> 1.156 | H9: =G9 -> 1.156 | I9: =H9 -> 1.156 | J9: =I9 -> 1.156 | K9: =J9 -> 1.156 | L9: =K9 -> 1.156 | ... Y9: =X9 -> 1.156
B10: 其他（亏损）/收益净额 | C10: Other gains and losses | D10: 0.096 | E10: =D10 -> 0.096 | F10: =E10 -> 0.096 | G10: =F10 -> 0.096 | H10: =G10 -> 0.096 | I10: =H10 -> 0.096 | J10: =I10 -> 0.096 | K10: =J10 -> 0.096 | L10: =K10 -> 0.096 | ... Y10: =X10 -> 0.096
A11: link | B11: 研发费用 | C11: Research and development expenses | D11: -18.442 | E11: =D11*(1+50%) -> -27.663 | F11: =E11*(1+50%) -> -41.4945 | G11: =F11*(1+40%) -> -58.0923 | H11: =G11*(1+40%) -> -81.32922 | I11: =H11*(1+40%) -> -113.86091 | J11: =I11*(1+30%) -> -148.01918 | K11: =J11*(1+10%) -> -162.8211 | L11: =K11*(1+8%) -> -175.84679 | M11: =L11*(1+6%) -> -186.39759 | N11: =M11*(1+4%) -> -193.8535 | O11: =N11*(1+2%) -> -197.73057 | P11: =O11*(1+1%) -> -199.70787 | Q11: =P11*(1+1%) -> -201.70495 | R11: =Q11*(1+1%) -> -203.722 | S11: =R11*(1+1%) -> -205.75922 | T11: =S11*(1+1%) -> -207.81681 | U11: =T11*(1+1%) -> -209.89498 | V11: =U11*(1+1%) -> -211.99393 | W11: =V11*(1+1%) -> -214.11387 | ... Y11: =X11*(1+1%) -> -218.41756
A12: link | B12: 行政开支 | C12: Administrative expenses | D12: -6.306 | E12: =D12*(1+50%) -> -9.459 | F12: =E12*(1+50%) -> -14.1885 | G12: =F12*(1+50%) -> -21.28275 | H12: =G12*(1+50%) -> -31.924125 | I12: =H12*(1+50%) -> -47.886187 | J12: =I12*(1+50%) -> -71.829281 | K12: =J12*(1+10%) -> -79.012209 | L12: =K12*(1+8%) -> -85.333186 | M12: =L12*(1+6%) -> -90.453177 | N12: =M12*(1+4%) -> -94.071304 | O12: =N12*(1+2%) -> -95.95273 | P12: =O12*(1+1%) -> -96.912258 | Q12: =P12*(1+1%) -> -97.88138 | R12: =Q12*(1+1%) -> -98.860194 | S12: =R12*(1+1%) -> -99.848796 | T12: =S12*(1+1%) -> -100.84728 | U12: =T12*(1+1%) -> -101.85576 | V12: =U12*(1+1%) -> -102.87431 | W12: =V12*(1+1%) -> -103.90306 | ... Y12: =X12*(1+1%) -> -105.99151
A13: link | B13: 销售费用 | C13: Selling expenses | D13: 0 | E13: 0 | F13: =-F6*Forecast!J5 -> #REF! | G13: =-G6*Forecast!K5 -> #REF! | H13: =-H6*30% -> #REF! | I13: =-I6*30% -> #REF! | J13: =-J6*20% -> #REF! | K13: =J13*(1+10%) -> #REF! | L13: =K13*(1+8%) -> #REF! | M13: =L13*(1+6%) -> #REF! | N13: =M13*(1+4%) -> #REF! | O13: =N13*(1+2%) -> #REF! | P13: =O13*(1+1%) -> #REF! | Q13: =P13*(1+1%) -> #REF! | R13: =Q13*(1+1%) -> #REF! | S13: =R13*(1+1%) -> #REF! | T13: =S13*(1+1%) -> #REF! | U13: =T13*(1+1%) -> #REF! | V13: =U13*(1+1%) -> #REF! | W13: =V13*(1+1%) -> #REF! | ... Y13: =X13*(1+1%) -> #REF!
B14: 经营亏损 | C14: Operating profits/(losses) | D14: =SUM(D8:D13) -> -23.496 | E14: =SUM(E8:E13) -> #REF! | F14: =SUM(F8:F13) -> #REF! | G14: =SUM(G8:G13) -> #REF! | H14: =SUM(H8:H13) -> #REF! | I14: =SUM(I8:I13) -> #REF! | J14: =SUM(J8:J13) -> #REF! | K14: =SUM(K8:K13) -> #REF! | ... Y14: =SUM(Y8:Y13) -> #REF!
C15: Fair value change of financial assets at fair value through profit or loss (FVTPL) | D15: 0.634 | E15: =D15 -> 0.634 | F15: =E15 -> 0.634 | G15: =F15 -> 0.634 | H15: =G15 -> 0.634 | I15: =H15 -> 0.634 | J15: =I15 -> 0.634 | K15: =J15 -> 0.634 | L15: =K15 -> 0.634 | ... Y15: =X15 -> 0.634
C16: Fair value change of financial liabilities at FVTPL | D16: 2.515 | E16: =D16 -> 2.515 | F16: =E16 -> 2.515 | G16: =F16 -> 2.515 | H16: =G16 -> 2.515 | I16: =H16 -> 2.515 | J16: =I16 -> 2.515 | K16: =J16 -> 2.515 | L16: =K16 -> 2.515 | ... Y16: =X16 -> 2.515
C17: Fair value change of convertible preferred shares | D17: -25.359 | E17: =D17 -> -25.359 | F17: =E17 -> -25.359 | G17: =F17 -> -25.359 | H17: =G17 -> -25.359 | I17: =H17 -> -25.359 | J17: =I17 -> -25.359 | K17: =J17 -> -25.359 | L17: =K17 -> -25.359 | ... Y17: =X17 -> -25.359
C18: Issuance cost of convertible preferred shares | D18: 0 | E18: =D18 -> 0 | F18: =E18 -> 0 | G18: =F18 -> 0 | H18: =G18 -> 0 | I18: =H18 -> 0 | J18: =I18 -> 0 | K18: =J18 -> 0 | L18: =K18 -> 0 | ... Y18: =X18 -> 0
B19: 财务费用 | C19: Finance cost | D19: -0.046 | E19: =Forecast!I34 -> 0 | F19: =Forecast!J34 -> 0 | G19: =Forecast!K34 -> 0 | H19: =Forecast!L34 -> 0 | I19: =Forecast!M34 -> 0 | J19: =Forecast!N34 -> 0 | K19: =Forecast!O34 -> 0 | L19: =Forecast!P34 -> 0 | ... Y19: =Forecast!AC34 -> 0
A20: link | B20: 财务收益 | C20: Finance income | D20: 0 | E20: =Forecast!I35 -> 0.76974 | F20: =Forecast!J35 -> #REF! | G20: =Forecast!K35 -> #REF! | H20: =Forecast!L35 -> #REF! | I20: =Forecast!M35 -> #REF! | J20: =Forecast!N35 -> #REF! | K20: =Forecast!O35 -> #REF! | L20: =Forecast!P35 -> #REF! | ... Y20: =Forecast!AC35 -> #REF!
B21: 财务成本净额 | C21: Finance income/(costs) — net | D21: =D20+D19 -> -0.046 | E21: =E20+E19 -> 0.76974 | F21: =F20+F19 -> #REF! | G21: =G20+G19 -> #REF! | H21: =H20+H19 -> #REF! | I21: =I20+I19 -> #REF! | J21: =J20+J19 -> #REF! | K21: =K20+K19 -> #REF! | ... Y21: =Y20+Y19 -> #REF!
B22: 除税前亏损 | C22: Loss before income tax | D22: =D14+D21+SUM(D15:D18) -> -45.752 | E22: =E14+E21+SUM(E15:E18) -> #REF! | F22: =F14+F21+SUM(F15:F18) -> #REF! | G22: =G14+G21+SUM(G15:G18) -> #REF! | H22: =H14+H21+SUM(H15:H18) -> #REF! | I22: =I14+I21+SUM(I15:I18) -> #REF! | J22: =J14+J21+SUM(J15:J18) -> #REF! | K22: =K14+K21+SUM(K15:K18) -> #REF! | ... Y22: =Y14+Y21+SUM(Y15:Y18) -> #REF!
B23: 所得税 | C23: Income tax (expense) credit | D23: -0.153 | E23: =IF(E22>0,-E22*0.25,0) -> #REF! | F23: =IF(F22>0,-F22*0.25,0) -> #REF! | G23: =IF(G22>0,-G22*0.25,0) -> #REF! | H23: =IF(H22>0,-H22*0.25,0) -> #REF! | I23: =IF(I22>0,-I22*0.25,0) -> #REF! | J23: =IF(J22>0,-J22*0.25,0) -> #REF! | K23: =IF(K22>0,-K22*0.25,0) -> #REF! | L23: =IF(L22>0,-L22*0.25,0) -> #REF! | ... Y23: =IF(Y22>0,-Y22*0.25,0) -> #REF!
B24: 净亏损 | C24: Net (loss)/profit | D24: =D22+D23 -> -45.905 | E24: =E22+E23 -> #REF! | F24: =F22+F23 -> #REF! | G24: =G22+G23 -> #REF! | H24: =H22+H23 -> #REF! | I24: =I22+I23 -> #REF! | J24: =J22+J23 -> #REF! | K24: =K22+K23 -> #REF! | ... Y24: =Y22+Y23 -> #REF!
B25: 归属普通股东净利润 | C25: Net (loss)/profit attributable to common shareholders | D25: =D24 -> -45.905 | E25: =E24 -> #REF! | F25: =F24 -> #REF! | G25: =G24 -> #REF! | H25: =H24 -> #REF! | I25: =I24 -> #REF! | J25: =J24 -> #REF! | K25: =K24 -> #REF! | ... Y25: =Y24 -> #REF!
B26: 每股收益 | C26: EPS | D26: -0.15 | E26: =E25/E27 -> #REF! | F26: =F25/F27 -> #REF! | G26: =G25/G27 -> #REF! | H26: =H25/H27 -> #REF! | I26: =I25/I27 -> #REF! | J26: =J25/J27 -> #REF! | K26: =K25/K27 -> #REF! | L26: =L25/L27 -> #REF! | ... Y26: =Y25/Y27 -> #REF!
C27: Shares O/S (mn) | D27: =D25/D26 -> 306.03333 | E27: =E181 -> 306.03333 | F27: =F181 -> 326.03333 | G27: =G181 -> 326.03333 | H27: =H181 -> 326.03333 | I27: =I181 -> 336.03333 | J27: =J181 -> 336.03333 | K27: =K181 -> 336.03333 | L27: =L181 -> 336.03333 | ... Y27: =Y181 -> 336.03333
B29: ARD.资产负债表(ORIG,百万元) | C29: Balance sheet | D29: 2019 | E29: 2020 | F29: 2021 | G29: 2022 | H29: 2023 | I29: 2024 | J29: 2025 | K29: 2026 | L29: 2027 | M29: 2028 | N29: 2029 | O29: 2030 | P29: 2031 | Q29: 2032 | R29: 2033 | S29: 2034 | T29: 2035 | U29: 2036 | V29: 2037 | W29: 2038 | X29: 2039 | Y29: 2040
B30: 其他应收款项、按金及预付款项 | C30: Deposits, prepayments and deferred expenses | D30: 1.179 | E30: =D30 -> 1.179 | F30: =E30 -> 1.179 | G30: =F30 -> 1.179 | H30: =G30 -> 1.179 | I30: =H30 -> 1.179 | J30: =I30 -> 1.179 | K30: =J30 -> 1.179 | L30: =K30 -> 1.179 | ... Y30: =X30 -> 1.179
A31: link forecast | B31: 贸易应收款项 | C31: Trade receivables | D31: 0 | E31: =E6*Forecast!I51/365 -> #REF! | F31: =F6*Forecast!J51/365 -> #REF! | G31: =G6*Forecast!K51/365 -> #REF! | H31: =H6*Forecast!L51/365 -> #REF! | I31: =I6*Forecast!M51/365 -> #REF! | J31: =J6*Forecast!N51/365 -> #REF! | K31: =K6*Forecast!O51/365 -> #REF! | L31: =L6*Forecast!P51/365 -> #REF! | ... Y31: =Y6*Forecast!AC51/365 -> #REF!
A32: link forecast | B32: 存货 | C32: Inventories | D32: 0 | E32: =-E7*Forecast!I52/365 -> #REF! | F32: =-F7*Forecast!J52/365 -> #REF! | G32: =-G7*Forecast!K52/365 -> #REF! | H32: =-H7*Forecast!L52/365 -> #REF! | I32: =-I7*Forecast!M52/365 -> #REF! | J32: =-J7*Forecast!N52/365 -> #REF! | K32: =-K7*Forecast!O52/365 -> #REF! | L32: =-L7*Forecast!P52/365 -> #REF! | ... Y32: =-Y7*Forecast!AC52/365 -> #REF!
C33: Loan to a director | D33: 0.131 | E33: 0 | F33: =E33 -> 0 | G33: =F33 -> 0 | H33: =G33 -> 0 | I33: =H33 -> 0 | J33: =I33 -> 0 | K33: =J33 -> 0 | L33: =K33 -> 0 | M33: =L33 -> 0 | ... Y33: =X33 -> 0
B34: 应收关联方款项 | C34: Amount due from subsidiaries | D34: 0 | E34: =D34 -> 0 | F34: =E34 -> 0 | G34: =F34 -> 0 | H34: =G34 -> 0 | I34: =H34 -> 0 | J34: =I34 -> 0 | K34: =J34 -> 0 | L34: =K34 -> 0 | ... Y34: =X34 -> 0
B35: 合同成本 | C35: Tax recoverable | D35: 0 | E35: =D35 -> 0 | F35: =E35 -> 0 | G35: =F35 -> 0 | H35: =G35 -> 0 | I35: =H35 -> 0 | J35: =I35 -> 0 | K35: =J35 -> 0 | L35: =K35 -> 0 | ... Y35: =X35 -> 0
C36: Financial assets at FVTPL | D36: 30.634 | E36: =D36 -> 30.634 | F36: =E36 -> 30.634 | G36: =F36 -> 30.634 | H36: =G36 -> 30.634 | I36: =H36 -> 30.634 | J36: =I36 -> 30.634 | K36: =J36 -> 30.634 | L36: =K36 -> 30.634 | ... Y36: =X36 -> 30.634
C37: Time deposits with original maturity over three months | D37: 5 | E37: =D37 -> 5 | F37: =E37 -> 5 | G37: =F37 -> 5 | H37: =G37 -> 5 | I37: =H37 -> 5 | J37: =I37 -> 5 | K37: =J37 -> 5 | L37: =K37 -> 5 | ... Y37: =X37 -> 5
B38: 现金及现金等价物 | C38: Cash and cash equivalents | D38: 38.487 | E38: =E114 -> #REF! | F38: =F114 -> #REF! | G38: =G114 -> #REF! | H38: =H114 -> #REF! | I38: =I114 -> #REF! | J38: =J114 -> #REF! | K38: =K114 -> #REF! | L38: =L114 -> #REF! | ... Y38: =Y114 -> #REF!
B39: 流动资产合计 | C39: Total current assets | D39: =SUM(D30:D38) -> 75.431 | E39: =SUM(E30:E38) -> #REF! | F39: =SUM(F30:F38) -> #REF! | G39: =SUM(G30:G38) -> #REF! | H39: =SUM(H30:H38) -> #REF! | I39: =SUM(I30:I38) -> #REF! | J39: =SUM(J30:J38) -> #REF! | K39: =SUM(K30:K38) -> #REF! | ... Y39: =SUM(Y30:Y38) -> #REF!
A40: link forecast | B40: 物业、厂房及设备 | C40: Plant and equipment | D40: 0.336 | E40: =Forecast!I87 -> 0.649 | F40: =Forecast!J87 -> 1.006 | G40: =Forecast!K87 -> 1.363 | H40: =Forecast!L87 -> 1.72 | I40: =Forecast!M87 -> 2.077 | J40: =Forecast!N87 -> 2.434 | K40: =Forecast!O87 -> 2.791 | L40: =Forecast!P87 -> 3.148 | ... Y40: =Forecast!AC87 -> 7.789
A41: link forecast | B41: 使用权资产 | C41: Right-of-use assets | D41: 1.674 | E41: =Forecast!I144 -> 3.157 | F41: =Forecast!J144 -> 4.64 | G41: =Forecast!K144 -> 6.123 | H41: =Forecast!L144 -> 7.606 | I41: =Forecast!M144 -> 9.089 | J41: =Forecast!N144 -> 10.572 | K41: =Forecast!O144 -> 12.055 | L41: =Forecast!P144 -> 13.538 | ... Y41: =Forecast!AC144 -> 36.847
A42: link forecast | B42: 无形资产 | C42: Intangible assets | D42: 1.338 | E42: =Forecast!I120 -> 10.301 | F42: =Forecast!J120 -> 18.264 | G42: =Forecast!K120 -> 25.227 | H42: =Forecast!L120 -> 31.19 | I42: =Forecast!M120 -> 36.153 | J42: =Forecast!N120 -> 40.116 | K42: =Forecast!O120 -> 43.079 | L42: =Forecast!P120 -> 45.042 | ... Y42: =Forecast!AC120 -> 254.561
C43: Rental deposits | D43: 0.096 | E43: =D43 -> 0.096 | F43: =E43 -> 0.096 | G43: =F43 -> 0.096 | H43: =G43 -> 0.096 | I43: =H43 -> 0.096 | J43: =I43 -> 0.096 | K43: =J43 -> 0.096 | L43: =K43 -> 0.096 | ... Y43: =X43 -> 0.096
B44: 递延所得税资产 | C44: Deferred income tax assets | D44: 0.178 | E44: =D44 -> 0.178 | F44: =E44 -> 0.178 | G44: =F44 -> 0.178 | H44: =G44 -> 0.178 | I44: =H44 -> 0.178 | J44: =I44 -> 0.178 | K44: =J44 -> 0.178 | L44: =K44 -> 0.178 | ... Y44: =X44 -> 0.178
B45: 其他应收款项、按金及预付款项 | C45: Investments in subsidiaries | D45: 0 | E45: =D45 -> 0 | F45: =E45 -> 0 | G45: =F45 -> 0 | H45: =G45 -> 0 | I45: =H45 -> 0 | J45: =I45 -> 0 | K45: =J45 -> 0 | L45: =K45 -> 0 | ... Y45: =X45 -> 0
B46: 非流动资产合计 | C46: Total non-current assets | D46: =SUM(D40:D45) -> 3.622 | E46: =SUM(E40:E45) -> 14.381 | F46: =SUM(F40:F45) -> 24.184 | G46: =SUM(G40:G45) -> 32.987 | H46: =SUM(H40:H45) -> 40.79 | I46: =SUM(I40:I45) -> 47.593 | J46: =SUM(J40:J45) -> 53.396 | K46: =SUM(K40:K45) -> 58.199 | ... Y46: =SUM(Y40:Y45) -> 299.471
B47: 资产总计 | C47: Total assets | D47: =D39+D46 -> 79.053 | E47: =E39+E46 -> #REF! | F47: =F39+F46 -> #REF! | G47: =G39+G46 -> #REF! | H47: =H39+H46 -> #REF! | I47: =I39+I46 -> #REF! | J47: =J39+J46 -> #REF! | K47: =K39+K46 -> #REF! | ... Y47: =Y39+Y46 -> #REF!
B48: 其他应付款和应计项目 | C48: Other payables and accruals | D48: 3.662 | E48: =D48 -> 3.662 | F48: =E48 -> 3.662 | G48: =F48 -> 3.662 | H48: =G48 -> 3.662 | I48: =H48 -> 3.662 | J48: =I48 -> 3.662 | K48: =J48 -> 3.662 | L48: =K48 -> 3.662 | ... Y48: =X48 -> 3.662
B49: 合同负债 | C49: Financial liabilities arising from unvested restricted shares | D49: 0.322 | E49: =D49 -> 0.322 | F49: =E49 -> 0.322 | G49: =F49 -> 0.322 | H49: =G49 -> 0.322 | I49: =H49 -> 0.322 | J49: =I49 -> 0.322 | K49: =J49 -> 0.322 | L49: =K49 -> 0.322 | ... Y49: =X49 -> 0.322
B50: 递延收入 | C50: Tax payable | D50: 0.148 | E50: =D50 -> 0.148 | F50: =E50 -> 0.148 | G50: =F50 -> 0.148 | H50: =G50 -> 0.148 | I50: =H50 -> 0.148 | J50: =I50 -> 0.148 | K50: =J50 -> 0.148 | L50: =K50 -> 0.148 | ... Y50: =X50 -> 0.148
B51: 租赁负债 | C51: Lease liabilities | D51: 0.446 | E51: =D51 -> 0.446 | F51: =E51 -> 0.446 | G51: =F51 -> 0.446 | H51: =G51 -> 0.446 | I51: =H51 -> 0.446 | J51: =I51 -> 0.446 | K51: =J51 -> 0.446 | L51: =K51 -> 0.446 | ... Y51: =X51 -> 0.446
A52: link forecast | B52: 贸易及其他应付款项 | C52: Trade payables | D52: 0 | E52: =-E7*Forecast!I53/365 -> #REF! | F52: =-F7*Forecast!J53/365 -> #REF! | G52: =-G7*Forecast!K53/365 -> #REF! | H52: =-H7*Forecast!L53/365 -> #REF! | I52: =-I7*Forecast!M53/365 -> #REF! | J52: =-J7*Forecast!N53/365 -> #REF! | K52: =-K7*Forecast!O53/365 -> #REF! | L52: =-L7*Forecast!P53/365 -> #REF! | ... Y52: =-Y7*Forecast!AC53/365 -> #REF!
C53: Other current liabilities | D53: 0 | E53: =E47-E62-E56-SUM(E48:E52)-1 -> #REF! | F53: =F47-F62-F56-SUM(F48:F52)-1 -> #REF! | G53: =G47-G62-G56-SUM(G48:G52)-1 -> #REF! | H53: =H47-H62-H56-SUM(H48:H52)-1 -> #REF! | I53: =I47-I62-I56-SUM(I48:I52)-1 -> #REF! | J53: =J47-J62-J56-SUM(J48:J52)-1 -> #REF! | K53: =K47-K62-K56-SUM(K48:K52)-1 -> #REF! | L53: =L47-L62-L56-SUM(L48:L52)-1 -> #REF! | ... Y53: =Y47-Y62-Y56-SUM(Y48:Y52)-1 -> #REF!
B54: 流动负债合计 | C54: Total current liabilities | D54: =SUM(D48:D53) -> 4.578 | E54: =SUM(E48:E53) -> #REF! | F54: =SUM(F48:F53) -> #REF! | G54: =SUM(G48:G53) -> #REF! | H54: =SUM(H48:H53) -> #REF! | I54: =SUM(I48:I53) -> #REF! | J54: =SUM(J48:J53) -> #REF! | K54: =SUM(K48:K53) -> #REF! | ... Y54: =SUM(Y48:Y53) -> #REF!
B55: 租赁负债 | C55: Lease liabilities | D55: 1.228 | E55: =D55 -> 1.228 | F55: =E55 -> 1.228 | G55: =F55 -> 1.228 | H55: =G55 -> 1.228 | I55: =H55 -> 1.228 | J55: =I55 -> 1.228 | K55: =J55 -> 1.228 | L55: =K55 -> 1.228 | ... Y55: =X55 -> 1.228
B56: 应付关联方款项 | C56: Convertible preferred shares | D56: 133.969 | E56: =D56 -> 133.969 | F56: =E56 -> 133.969 | G56: =F56 -> 133.969 | H56: =G56 -> 133.969 | I56: =H56 -> 133.969 | J56: =I56 -> 133.969 | K56: =J56 -> 133.969 | L56: =K56 -> 133.969 | ... Y56: =X56 -> 133.969
B57: 非流动负债合计 | C57: Total non-current liabilities | D57: =SUM(D55:D56) -> 135.197 | E57: =SUM(E55:E56) -> 135.197 | F57: =SUM(F55:F56) -> 135.197 | G57: =SUM(G55:G56) -> 135.197 | H57: =SUM(H55:H56) -> 135.197 | I57: =SUM(I55:I56) -> 135.197 | J57: =SUM(J55:J56) -> 135.197 | K57: =SUM(K55:K56) -> 135.197 | ... Y57: =SUM(Y55:Y56) -> 135.197
B58: 负债合计 | C58: Total liabilities | D58: =D54+D57 -> 139.775 | E58: =E54+E57 -> #REF! | F58: =F54+F57 -> #REF! | G58: =G54+G57 -> #REF! | H58: =H54+H57 -> #REF! | I58: =I54+I57 -> #REF! | J58: =J54+J57 -> #REF! | K58: =K54+K57 -> #REF! | ... Y58: =Y54+Y57 -> #REF!
B59: 股本 | C59: Share capital | D59: 0.036 | E59: =D59+E140+E154 -> 0.036 | F59: =E59+F140+F154 -> 0.038 | G59: =F59+G140+G154 -> 0.038 | H59: =G59+H140+H154 -> 0.038 | I59: =H59+I140+I154 -> 0.039 | J59: =I59+J140+J154 -> 0.039 | K59: =J59+K140+K154 -> 0.039 | L59: =K59+L140+L154 -> 0.039 | ... Y59: =X59+Y140+Y154 -> 0.039
B60: 股本溢价 | C60: Treasury shares | D60: -0.322 | E60: 0 | F60: =E60 -> 0 | G60: =F60 -> 0 | H60: =G60 -> 0 | I60: =H60 -> 0 | J60: =I60 -> 0 | K60: =J60 -> 0 | L60: =K60 -> 0 | M60: =L60 -> 0 | ... Y60: =X60 -> 0
B61: 储备 | C61: Reserves | D61: -60.436 | E61: =D61+E81+E24+E141 -> #REF! | F61: =E61+F81+F24+F141 -> #REF! | G61: =F61+G81+G24+G141 -> #REF! | H61: =G61+H81+H24+H141 -> #REF! | I61: =H61+I81+I24+I141 -> #REF! | J61: =I61+J81+J24+J141 -> #REF! | K61: =J61+K81+K24+K141 -> #REF! | L61: =K61+L81+L24+L141 -> #REF! | ... Y61: =X61+Y81+Y24+Y141 -> #REF!
B62: 股东权益合计 | C62: Total shareholders’ equity | D62: -60.722 | E62: =SUM(E59:E61) -> #REF! | F62: =SUM(F59:F61) -> #REF! | G62: =SUM(G59:G61) -> #REF! | H62: =SUM(H59:H61) -> #REF! | I62: =SUM(I59:I61) -> #REF! | J62: =SUM(J59:J61) -> #REF! | K62: =SUM(K59:K61) -> #REF! | L62: =SUM(L59:L61) -> #REF! | ... Y62: =SUM(Y59:Y61) -> #REF!
B63: 总负债及股东权益总额 | C63: Total liabilities and Shareholders'Equity | D63: =D58+D62 -> 79.053 | E63: =E58+E62 -> #REF! | F63: =F58+F62 -> #REF! | G63: =G58+G62 -> #REF! | H63: =H58+H62 -> #REF! | I63: =I58+I62 -> #REF! | J63: =J58+J62 -> #REF! | K63: =K58+K62 -> #REF! | ... Y63: =Y58+Y62 -> #REF!
C64: Balance check | D64: =IF(D63-D47=0,"ok",D63-D47) -> -1.4210855e-14 | E64: =IF(E63-E47=0,"ok",E63-E47) -> #REF! | F64: =IF(F63-F47=0,"ok",F63-F47) -> #REF! | G64: =IF(G63-G47=0,"ok",G63-G47) -> #REF! | H64: =IF(H63-H47=0,"ok",H63-H47) -> #REF! | I64: =IF(I63-I47=0,"ok",I63-I47) -> #REF! | J64: =IF(J63-J47=0,"ok",J63-J47) -> #REF! | K64: =IF(K63-K47=0,"ok",K63-K47) -> #REF! | ... Y64: =IF(Y63-Y47=0,"ok",Y63-Y47) -> #REF!
B69: ARD.现金流量表(ORIG,百万元) | C69: Cash flow statement | D69: 2019 | E69: 2020 | F69: 2021 | G69: 2022 | H69: 2023 | I69: 2024 | J69: 2025 | K69: 2026 | L69: 2027 | M69: 2028 | N69: 2029 | O69: 2030 | P69: 2031 | Q69: 2032 | R69: 2033 | S69: 2034 | T69: 2035 | U69: 2036 | V69: 2037 | W69: 2038 | X69: 2039 | Y69: 2040
B70: 净利润 | C70: Net loss | D70: =D22 -> -45.752 | E70: =E22 -> #REF! | F70: =F22 -> #REF! | G70: =G22 -> #REF! | H70: =H22 -> #REF! | I70: =I22 -> #REF! | J70: =J22 -> #REF! | K70: =K22 -> #REF! | ... Y70: =Y22 -> #REF!
B71: 非现金支付: | C71: Adjustments for non-cash charges | D71: =SUM(D72:D82) -> 22.141 | E71: =SUM(E72:E82) -> 24.54674 | F71: =SUM(F72:F82) -> #REF! | G71: =SUM(G72:G82) -> #REF! | H71: =SUM(H72:H82) -> #REF! | I71: =SUM(I72:I82) -> #REF! | J71: =SUM(J72:J82) -> #REF! | K71: =SUM(K72:K82) -> #REF! | ... Y71: =SUM(Y72:Y82) -> #REF!
A72: link forecast | B72: 利息收入 | C72: Interest income | D72: -0.702 | E72: =Forecast!I35 -> 0.76974 | F72: =Forecast!J35 -> #REF! | G72: =Forecast!K35 -> #REF! | H72: =Forecast!L35 -> #REF! | I72: =Forecast!M35 -> #REF! | J72: =Forecast!N35 -> #REF! | K72: =Forecast!O35 -> #REF! | L72: =Forecast!P35 -> #REF! | ... Y72: =Forecast!AC35 -> #REF!
A73: link forecast | B73: 物业、厂房及设备折旧 | C73: Depreciation of property, plant and equipment | D73: 0.039 | E73: =Forecast!I79 -> 0.039 | F73: =Forecast!J79 -> 0.039 | G73: =Forecast!K79 -> 0.039 | H73: =Forecast!L79 -> 0.039 | I73: =Forecast!M79 -> 0.039 | J73: =Forecast!N79 -> 0.039 | K73: =Forecast!O79 -> 0.039 | L73: =Forecast!P79 -> 0.039 | ... Y73: =Forecast!AC79 -> 0.039
C74: Depreciation of right-of-use assets | D74: 0.31 | E74: =Forecast!I137 -> 0.31 | F74: =Forecast!J137 -> 0.31 | G74: =Forecast!K137 -> 0.31 | H74: =Forecast!L137 -> 0.31 | I74: =Forecast!M137 -> 0.31 | J74: =Forecast!N137 -> 0.31 | K74: =Forecast!O137 -> 0.31 | L74: =Forecast!P137 -> 0.31 | ... Y74: =Forecast!AC137 -> 0
A75: link forecast | B75: 使用权资产和无形资产摊销 | C75: Amortization of intangible assets | D75: 0.02 | E75: =Forecast!I105 -> 1 | F75: =Forecast!J105 -> 1 | G75: =Forecast!K105 -> 1 | H75: =Forecast!L105 -> 1 | I75: =Forecast!M105 -> 1 | J75: =Forecast!N105 -> 1 | K75: =Forecast!O105 -> 1 | L75: =Forecast!P105 -> 1 | ... Y75: =Forecast!AC105 -> 1
C76: Impairment loss of intangible assets | D76: 0 | E76: =D76 -> 0 | F76: =E76 -> 0 | G76: =F76 -> 0 | H76: =G76 -> 0 | I76: =H76 -> 0 | J76: =I76 -> 0 | K76: =J76 -> 0 | L76: =K76 -> 0 | ... Y76: =X76 -> 0
C77: Fair value change of financial liabilities at FVTPL | D77: -2.515 | E77: =-E16 -> -2.515 | F77: =-F16 -> -2.515 | G77: =-G16 -> -2.515 | H77: =-H16 -> -2.515 | I77: =-I16 -> -2.515 | J77: =-J16 -> -2.515 | K77: =-K16 -> -2.515 | L77: =-L16 -> -2.515 | ... Y77: =-Y16 -> -2.515
C78: Fair value change of financial asset at FVTPL | D78: -0.634 | E78: =-E15 -> -0.634 | F78: =-F15 -> -0.634 | G78: =-G15 -> -0.634 | H78: =-H15 -> -0.634 | I78: =-I15 -> -0.634 | J78: =-J15 -> -0.634 | K78: =-K15 -> -0.634 | L78: =-L15 -> -0.634 | ... Y78: =-Y15 -> -0.634
C79: Fair value change of convertible preferred shares | D79: 25.359 | E79: =-E17 -> 25.359 | F79: =-F17 -> 25.359 | G79: =-G17 -> 25.359 | H79: =-H17 -> 25.359 | I79: =-I17 -> 25.359 | J79: =-J17 -> 25.359 | K79: =-K17 -> 25.359 | L79: =-L17 -> 25.359 | ... Y79: =-Y17 -> 25.359
B80: 财务费用 | C80: Financial cost | D80: 0.046 | E80: =-E19 -> 0 | F80: =-F19 -> 0 | G80: =-G19 -> 0 | H80: =-H19 -> 0 | I80: =-I19 -> 0 | J80: =-J19 -> 0 | K80: =-K19 -> 0 | L80: =-L19 -> 0 | ... Y80: =-Y19 -> 0
B81: 非现金股份支付费用 | C81: Non-cash share-based payment expense | D81: 0.218 | E81: =D81 -> 0.218 | F81: =E81 -> 0.218 | G81: =F81 -> 0.218 | H81: =G81 -> 0.218 | I81: =H81 -> 0.218 | J81: =I81 -> 0.218 | K81: =J81 -> 0.218 | L81: =K81 -> 0.218 | ... Y81: =X81 -> 0.218
C82: Issuance costs for convertible preferred shares | D82: 0 | E82: =-E18 -> 0 | F82: =-F18 -> 0 | G82: =-G18 -> 0 | H82: =-H18 -> 0 | I82: =-I18 -> 0 | J82: =-J18 -> 0 | K82: =-K18 -> 0 | L82: =-L18 -> 0 | ... Y82: =-Y18 -> 0
C83: Operating cash flows before movements in working capital | D83: -23.611 | E83: =SUM(E70:E71) -> #REF! | F83: =SUM(F70:F71) -> #REF! | G83: =SUM(G70:G71) -> #REF! | H83: =SUM(H70:H71) -> #REF! | I83: =SUM(I70:I71) -> #REF! | J83: =SUM(J70:J71) -> #REF! | K83: =SUM(K70:K71) -> #REF! | L83: =SUM(L70:L71) -> #REF! | ... Y83: =SUM(Y70:Y71) -> #REF!
B84: 营业资金变动： | C84: Changes in working capital: | D84: =SUM(D85:D89) -> 1.11 | E84: =SUM(E85:E89) -> #REF! | F84: =SUM(F85:F89) -> #REF! | G84: =SUM(G85:G89) -> #REF! | H84: =SUM(H85:H89) -> #REF! | I84: =SUM(I85:I89) -> #REF! | J84: =SUM(J85:J89) -> #REF! | K84: =SUM(K85:K89) -> #REF! | ... Y84: =SUM(Y85:Y89) -> #REF!
B85: 其他应收款项、押金和预付款项 | C85: (Increase) decrease in deposits, prepayments and deferred expenses | D85: -0.334 | E85: =E30-D30 -> 0 | F85: =F30-E30 -> 0 | G85: =G30-F30 -> 0 | H85: =H30-G30 -> 0 | I85: =I30-H30 -> 0 | J85: =J30-I30 -> 0 | K85: =K30-J30 -> 0 | L85: =L30-K30 -> 0 | ... Y85: =Y30-X30 -> 0
B86: 应计项目和其他应付款项 | C86: Increase in other payables and accruals | D86: 1.444 | E86: =D48-E48 -> 0 | F86: =E48-F48 -> 0 | G86: =F48-G48 -> 0 | H86: =G48-H48 -> 0 | I86: =H48-I48 -> 0 | J86: =I48-J48 -> 0 | K86: =J48-K48 -> 0 | L86: =K48-L48 -> 0 | ... Y86: =X48-Y48 -> 0
B87: 存货 | C87: Inventories | D87: 0 | E87: =E32-D32 -> #REF! | F87: =F32-E32 -> #REF! | G87: =G32-F32 -> #REF! | H87: =H32-G32 -> #REF! | I87: =I32-H32 -> #REF! | J87: =J32-I32 -> #REF! | K87: =K32-J32 -> #REF! | L87: =L32-K32 -> #REF! | ... Y87: =Y32-X32 -> #REF!
B88: 应收账款 | C88: Trade receivables | D88: 0 | E88: =E31-D31 -> #REF! | F88: =F31-E31 -> #REF! | G88: =G31-F31 -> #REF! | H88: =H31-G31 -> #REF! | I88: =I31-H31 -> #REF! | J88: =J31-I31 -> #REF! | K88: =K31-J31 -> #REF! | L88: =L31-K31 -> #REF! | ... Y88: =Y31-X31 -> #REF!
B89: 贸易应付款项 | C89: Trade payables | D89: 0 | E89: =E52-D52 -> #REF! | F89: =F52-E52 -> #REF! | G89: =G52-F52 -> #REF! | H89: =H52-G52 -> #REF! | I89: =I52-H52 -> #REF! | J89: =J52-I52 -> #REF! | K89: =K52-J52 -> #REF! | L89: =L52-K52 -> #REF! | ... Y89: =Y52-X52 -> #REF!
B90: 经营活动产生的现金流 | C90: Cash (used in)/generated from operating activities | D90: =D83+D84 -> -22.501 | E90: =E83+E84 -> #REF! | F90: =F83+F84 -> #REF! | G90: =G83+G84 -> #REF! | H90: =H83+H84 -> #REF! | I90: =I83+I84 -> #REF! | J90: =J83+J84 -> #REF! | K90: =K83+K84 -> #REF! | ... Y90: =Y83+Y84 -> #REF!
B91: 所得税支出 | C91: Income tax paid | D91: -0.095 | E91: =D23 -> -0.153 | F91: =E23 -> #REF! | G91: =F23 -> #REF! | H91: =G23 -> #REF! | I91: =H23 -> #REF! | J91: =I23 -> #REF! | K91: =J23 -> #REF! | L91: =K23 -> #REF! | ... Y91: =X23 -> #REF!
B92: 经营活动产生的现金流量净额 | C92: Net cash (used in) operating activities | D92: =SUM(D90:D91) -> -22.596 | E92: =SUM(E90:E91) -> #REF! | F92: =SUM(F90:F91) -> #REF! | G92: =SUM(G90:G91) -> #REF! | H92: =SUM(H90:H91) -> #REF! | I92: =SUM(I90:I91) -> #REF! | J92: =SUM(J90:J91) -> #REF! | K92: =SUM(K90:K91) -> #REF! | ... Y92: =SUM(Y90:Y91) -> #REF!
C94: Interest received | D94: 0.699 | E94: =D94 -> 0.699 | F94: =E94 -> 0.699 | G94: =F94 -> 0.699 | H94: =G94 -> 0.699 | I94: =H94 -> 0.699 | J94: =I94 -> 0.699 | K94: =J94 -> 0.699 | L94: =K94 -> 0.699 | ... Y94: =X94 -> 0.699
C95: Proceeds from redemption of time deposits with original maturity over three months | D95: 20.4 | E95: =D95 -> 20.4 | F95: =E95 -> 20.4 | G95: =F95 -> 20.4 | H95: =G95 -> 20.4 | I95: =H95 -> 20.4 | J95: =I95 -> 20.4 | K95: =J95 -> 20.4 | L95: =K95 -> 20.4 | ... Y95: =X95 -> 20.4
B96: 购买物业、厂房及设备 | C96: Payments for property, plant and equipment | D96: -0.357 | E96: =-(E40-D40) -> -0.313 | F96: =-(F40-E40) -> -0.357 | G96: =-(G40-F40) -> -0.357 | H96: =-(H40-G40) -> -0.357 | I96: =-(I40-H40) -> -0.357 | J96: =-(J40-I40) -> -0.357 | K96: =-(K40-J40) -> -0.357 | L96: =-(L40-K40) -> -0.357 | ... Y96: =-(Y40-X40) -> -0.357
A97: link forecast | B97: 购买无形资产 | C97: Payments of intangible assets | D97: -0.5 | E97: =-Forecast!I97 -> -10 | F97: =-Forecast!J97 -> -10 | G97: =-Forecast!K97 -> -10 | H97: =-Forecast!L97 -> -10 | I97: =-Forecast!M97 -> -10 | J97: =-Forecast!N97 -> -10 | K97: =-Forecast!O97 -> -10 | L97: =-Forecast!P97 -> -10 | ... Y97: =-Forecast!AC97 -> -10
C98: Payment for acquisition of financial asset at FVTPL | D98: -70 | E98: 0 | F98: =E98 -> 0 | G98: =F98 -> 0 | H98: =G98 -> 0 | I98: =H98 -> 0 | J98: =I98 -> 0 | K98: =J98 -> 0 | L98: =K98 -> 0 | M98: =L98 -> 0 | ... Y98: =X98 -> 0
B99: 出售物业、厂房及设备所得款项 | C99: Proceeds from disposal of financial asset at FVTPL | D99: 40 | E99: 0 | F99: =E99 -> 0 | G99: =F99 -> 0 | H99: =G99 -> 0 | I99: =H99 -> 0 | J99: =I99 -> 0 | K99: =J99 -> 0 | L99: =K99 -> 0 | M99: =L99 -> 0 | ... Y99: =X99 -> 0
C100: Payment for rental deposits | D100: -0.005 | E100: =-(E43-D43) -> 0 | F100: =-(F43-E43) -> 0 | G100: =-(G43-F43) -> 0 | H100: =-(H43-G43) -> 0 | I100: =-(I43-H43) -> 0 | J100: =-(J43-I43) -> 0 | K100: =-(K43-J43) -> 0 | L100: =-(L43-K43) -> 0 | ... Y100: =-(Y43-X43) -> 0
C101: Placement of time deposits with original maturity over three months | D101: -19.4 | E101: 0 | F101: =E101 -> 0 | G101: =F101 -> 0 | H101: =G101 -> 0 | I101: =H101 -> 0 | J101: =I101 -> 0 | K101: =J101 -> 0 | L101: =K101 -> 0 | M101: =L101 -> 0 | ... Y101: =X101 -> 0
C102: Repayment of loan to a director | D102: 0 | E102: =E33-D33 -> -0.131 | F102: =F33-E33 -> 0 | G102: =G33-F33 -> 0 | H102: =H33-G33 -> 0 | I102: =I33-H33 -> 0 | J102: =J33-I33 -> 0 | K102: =K33-J33 -> 0 | L102: =L33-K33 -> 0 | ... Y102: =Y33-X33 -> 0
B103: 投资活动产生的现金流量净额 | C103: Net cash (used in) investing activities | D103: =SUM(D94:D102) -> -29.163 | E103: =SUM(E94:E102) -> 10.655 | F103: =SUM(F94:F102) -> 10.742 | G103: =SUM(G94:G102) -> 10.742 | H103: =SUM(H94:H102) -> 10.742 | I103: =SUM(I94:I102) -> 10.742 | J103: =SUM(J94:J102) -> 10.742 | K103: =SUM(K94:K102) -> 10.742 | ... Y103: =SUM(Y94:Y102) -> 10.742
B104: 发行股份所得款项 | C104: Other proceeds | D104: 12.2 | E104: =E139 -> 0 | F104: =F139 -> 200 | G104: =G153 -> 0 | H104: =H153 -> 0 | I104: =I153 -> 100 | J104: =J153 -> 0 | K104: =K153 -> 0 | L104: =L153 -> 0 | M104: =M153 -> 0 | N104: =N153 -> 0 | ... Y104: =Y153 -> 0
B105: 发行股份所得款项 | C105: Proceeds from issue of shares upon exercise of share options | D105: 0.002 | E105: 0 | F105: =E105 -> 0 | G105: =F105 -> 0 | H105: =G105 -> 0 | I105: =H105 -> 0 | J105: =I105 -> 0 | K105: =J105 -> 0 | L105: =K105 -> 0 | M105: =L105 -> 0 | ... Y105: =X105 -> 0
B106: 支付给关联方的利息 | C106: Interest paid | D106: -0.046 | E106: 0 | F106: =E106 -> 0 | G106: =F106 -> 0 | H106: =G106 -> 0 | I106: =H106 -> 0 | J106: =I106 -> 0 | K106: =J106 -> 0 | L106: =K106 -> 0 | M106: =L106 -> 0 | ... Y106: =X106 -> 0
...

Sheet APL101
B1: Unit | F1: US
F2: mn | G2: 2010 | H2: 2011 | I2: 2012 | J2: 2013 | K2: 2014 | L2: 2015 | M2: 2016 | N2: 2017 | O2: 2018 | P2: 2019 | Q2: 2020E | R2: 2021E | S2: 2022E | T2: 2023E | U2: 2024E | V2: 2025E | W2: 2026E | X2: 2027E | Y2: 2028E | Z2: 2029E | AA2: 2030E | AB2: 2031E | AC2: 2032E | AD2: 2033E | AE2: 2034E | AF2: 2035E | AG2: 2036E | AH2: 2037E | AI2: 2038E | AJ2: 2039E | AK2: 2040E
F3: Female population | G3: 156.55756 | H3: 157.64654 | I3: 158.7464 | J3: 159.78632 | K3: 160.9033 | L3: 162.04331 | M3: 163.18003 | N3: 164.19369 | O3: 165.04257 | P3: 165.82164 | Q3: =Q7-Q5 -> 166.64513 | R3: =R7-R5 -> 167.43682 | S3: =S7-S5 -> 168.23228 | T3: =T7-T5 -> 169.03151 | U3: =U7-U5 -> 169.83455 | V3: =V7-V5 -> 170.64139 | W3: =W7-W5 -> 171.45207 | X3: =X7-X5 -> 172.26661 | ... AK3: =AK7-AK5 -> 183.21444
F4: y/y growth | H4: =H3/G3 -> 1.0069558 | I4: =I3/H3 -> 1.0069767 | J4: =J3/I3 -> 1.0065508 | K4: 0.005 | L4: =L3/K3-1 -> 0.0070850317 | M4: =M3/L3-1 -> 0.0070148963 | N4: =N3/M3-1 -> 0.0062119184 | O4: =O3/N3-1 -> 0.0051700344 | P4: =P3/O3-1 -> 0.0047204063 | Q4: =Q3/P3-1 -> 0.004966094 | R4: =R3/Q3-1 -> 0.0047507848 | S4: =S3/R3-1 -> 0.0047507848 | ... AK4: =AK3/AJ3-1 -> 0.0047507848
F5: Male population | G5: 152.76411 | H5: 153.91033 | I5: 155.08459 | J5: 156.2074 | K5: 157.39771 | L5: 158.59186 | M5: 159.76129 | N5: 160.79185 | O5: 161.64493 | P5: 162.41788 | Q5: =Q7/(Q9+1) -> 163.15379 | R5: =R7/(R9+1) -> 163.9289 | S5: =S7/(S9+1) -> 164.70769 | T5: =T7/(T9+1) -> 165.49018 | U5: =U7/(U9+1) -> 166.27639 | V5: =V7/(V9+1) -> 167.06633 | W5: =W7/(W9+1) -> 167.86003 | X5: =X7/(X9+1) -> 168.6575 | ... AK5: =AK7/(AK9+1) -> 179.37597
F6: y/y growth | H6: =H5/G5 -> 1.0075032 | I6: =I5/H5 -> 1.0076295 | J6: 0.0047 | K6: 0.0047 | L6: 0.0047 | M6: =M5/L5-1 -> 0.0073738402 | N6: =N5/M5-1 -> 0.0064506679 | O6: =O5/N5-1 -> 0.0053054616 | P6: =P5/O5-1 -> 0.0047818018 | Q6: =Q5/P5-1 -> 0.0045309634 | R6: =R5/Q5-1 -> 0.0047507848 | S6: =S5/R5-1 -> 0.0047507848 | T6: =T5/S5-1 -> 0.0047507848 | ... AK6: =AK5/AJ5-1 -> 0.0047507848
B7: Inputs | F7: Total population | G7: 309.32167 | H7: 311.55687 | I7: 313.83099 | J7: 315.99372 | K7: 318.30101 | L7: 320.63516 | M7: 322.94131 | N7: 324.98554 | O7: 326.6875 | P7: 328.23952 | Q7: =P7*(1+Q8) -> 329.79892 | R7: =Q7*(1+R8) -> 331.36572 | S7: =R7*(1+S8) -> 332.93997 | T7: =S7*(1+T8) -> 334.5217 | U7: =T7*(1+U8) -> 336.11094 | V7: =U7*(1+V8) -> 337.70773 | W7: =V7*(1+W8) -> 339.3121 | X7: =W7*(1+X8) -> 340.9241 | ... AK7: =AJ7*(1+AK8) -> 362.59041
F8: y/y growth | H8: =H7/G7-1 -> 0.0072261605 | I8: =I7/H7-1 -> 0.0072992002 | J8: =J7/I7-1 -> 0.0068913685 | K8: =K7/J7-1 -> 0.0073017054 | L8: =L7/K7-1 -> 0.0073331687 | M8: =M7/L7-1 -> 0.0071924363 | N8: =N7/M7-1 -> 0.0063300294 | O8: =O7/N7-1 -> 0.0052370392 | P8: =P7/O7-1 -> 0.0047507848 | Q8: =P8 -> 0.0047507848 | R8: =Q8 -> 0.0047507848 | S8: =R8 -> 0.0047507848 | T8: =S8 -> 0.0047507848 | U8: =T8 -> 0.0047507848 | V8: =U8 -> 0.0047507848 | W8: =V8 -> 0.0047507848 | X8: =W8 -> 0.0047507848 | ... AK8: =AJ8 -> 0.0047507848
F9: Sex ration | G9: =G3/G5 -> 1.0248321 | H9: =H3/H5 -> 1.0242753 | I9: =I3/I5 -> 1.0236117 | J9: =J3/J5 -> 1.0229113 | K9: =K3/K5 -> 1.0222722 | L9: =L3/L5 -> 1.0217631 | M9: =M3/M5 -> 1.021399 | N9: =M9 -> 1.021399 | O9: =N9 -> 1.021399 | P9: =O9 -> 1.021399 | Q9: =P9 -> 1.021399 | R9: =Q9 -> 1.021399 | S9: =R9 -> 1.021399 | T9: =S9 -> 1.021399 | U9: =T9 -> 1.021399 | ... AK9: =AJ9 -> 1.021399
F13: Non-Small Cell Lung Cancer | G13: 2010 | H13: 2011 | I13: 2012 | J13: 2013 | K13: 2014 | L13: 2015 | M13: 2016 | N13: 2017 | O13: 2018 | P13: 2019 | Q13: 2020E | R13: 2021E | S13: 2022E | T13: 2023E | U13: 2024E | V13: 2025E | W13: 2026E | X13: 2027E | Y13: 2028E | Z13: 2029E | AA13: 2030E | AB13: 2031E | AC13: 2032E | AD13: 2033E | AE13: 2034E | AF13: 2035E | AG13: 2036E | AH13: 2037E | AI13: 2038E | AJ13: 2039E | AK13: 2040E | AL13: Ph 2 CT
F14: US
F15: Incidence rate (per 100 000) lung cancer | G15: =H15/1.05 -> 29.617289 | H15: =I15/1.05 -> 31.098154 | I15: =J15/1.05 -> 32.653061 | J15: =K15/1.05 -> 34.285714 | K15: 36 | L15: =K15*1.05 -> 37.8 | M15: =L15*1.05 -> 39.69 | N15: =M15*1.05 -> 41.6745 | O15: =N15*1.05 -> 43.758225 | P15: =O15*1.05 -> 45.946136 | Q15: =P15*1.05 -> 48.243443 | R15: =Q15*1.05 -> 50.655615 | S15: =R15*1.05 -> 53.188396 | ... AK15: =AJ15*1.05 -> 128.00422
F16: Annual Incidence ('000) | G16: =G15*G7/100 -> 91.612692 | H16: =H15*H7/100 -> 96.888435 | I16: =I15*I7/100 -> 102.47543 | J16: =J15*J7/100 -> 108.3407 | K16: =K15*K7/100 -> 114.58836 | L16: =L15*L7/100 -> 121.20009 | M16: =M15*M7/100 -> 128.17541 | N16: =N15*N7/100 -> 135.4361 | ... AK16: =AK15*AK7/100 -> 464.13101
F18: NSCLC as % of lung cancer | G18: 0.8 | H18: 0.8 | I18: 0.8 | J18: 0.8 | K18: 0.8 | L18: 0.8 | M18: 0.8 | N18: 0.8 | O18: 0.8 | P18: 0.8 | Q18: 0.8 | R18: 0.8 | S18: 0.8 | T18: 0.8 | U18: 0.8 | V18: 0.8 | W18: 0.8 | X18: 0.8 | Y18: 0.8 | Z18: 0.8 | AA18: 0.8 | AB18: 0.8 | AC18: 0.8 | AD18: 0.8 | AE18: 0.8 | AF18: 0.8 | AG18: 0.8 | AH18: 0.8 | AI18: 0.8 | AJ18: 0.8 | AK18: 0.8
B19: Stage completed | C19: 4 | D19: =VLOOKUP(C19,B23:D29,3) -> Phase 2 | F19: NSCLC Incidence ('000) | G19: =G16*G18 -> 73.290154 | H19: =H16*H18 -> 77.510748 | I19: =I16*I18 -> 81.98034 | J19: =J16*J18 -> 86.672562 | K19: =K16*K18 -> 91.67069 | L19: =L16*L18 -> 96.960073 | M19: =M16*M18 -> 102.54033 | N19: =N16*N18 -> 108.34888 | ... AK19: =AK16*AK18 -> 371.30481
B21: Commercialization timeline (stage starts on Year) | F21: Stage IIIb & IV as % of total NSCLC | G21: 0.75 | H21: =G21-0.01 -> 0.74 | I21: =H21-0.01 -> 0.73 | J21: =I21-0.01 -> 0.72 | K21: =J21-0.01 -> 0.71 | L21: =K21-0.01 -> 0.7 | M21: =L21-0.01 -> 0.69 | N21: =M21-0.01 -> 0.68 | O21: =N21-0.01 -> 0.67 | ... AK21: =AJ21-0.01 -> 0.45
B22: Stage No. | F22: # of Stage IIIb & IV case ('000) | G22: =G21*G19 -> 54.967615 | H22: =H21*H19 -> 57.357954 | I22: =I21*I19 -> 59.845648 | J22: =J21*J19 -> 62.404245 | K22: =K21*K19 -> 65.08619 | L22: =L21*L19 -> 67.872051 | M22: =M21*M19 -> 70.752824 | N22: =N21*N19 -> 73.677238 | ... AK22: =AK21*AK19 -> 167.08716
B23: 1 | D23: Pre-clinical | F23: % of late stage patient with PS<= 2 | G23: 0.65 | H23: =G23+0.01 -> 0.66 | I23: =H23+0.01 -> 0.67 | J23: =I23+0.01 -> 0.68 | K23: =J23+0.01 -> 0.69 | L23: =K23+0.01 -> 0.7 | M23: =L23+0.01 -> 0.71 | N23: =M23+0.01 -> 0.72 | O23: =N23+0.01 -> 0.73 | ... AK23: =AJ23+0.01 -> 0.95
B24: 2 | D24: IND Filing | F24: # of late-stage patient suitable for chemo ('000) | G24: =G23*G22 -> 35.72895 | H24: =H23*H22 -> 37.856249 | I24: =I23*I22 -> 40.096584 | J24: =J23*J22 -> 42.434886 | K24: =K23*K22 -> 44.909471 | L24: =L23*L22 -> 47.510436 | M24: =M23*M22 -> 50.234505 | N24: =N23*N22 -> 53.047611 | ... AK24: =AK23*AK22 -> 158.73281
B25: 3 | D25: Phase 1
B26: 4 | C26: 2021 | D26: Phase 2 | F26: Stage I, II & IIIa as % of total NSCLC | G26: 0.25 | H26: =G26+0.01 -> 0.26 | I26: =H26+0.01 -> 0.27 | J26: =I26+0.01 -> 0.28 | K26: =J26+0.01 -> 0.29 | L26: =K26+0.01 -> 0.3 | M26: =L26+0.01 -> 0.31 | N26: =M26+0.01 -> 0.32 | O26: =N26+0.01 -> 0.33 | ... AK26: =AJ26+0.01 -> 0.55
B27: 5 | C27: 2022 | D27: Phase 3 | F27: # of Stage I, II & IIIa case - Surgery ('000) | G27: =G26*G19 -> 18.322538 | H27: =H26*H19 -> 20.152794 | I27: =I26*I19 -> 22.134692 | J27: =J26*J19 -> 24.268317 | K27: =K26*K19 -> 26.5845 | L27: =L26*L19 -> 29.088022 | M27: =M26*M19 -> 31.787501 | N27: =N26*N19 -> 34.671641 | ... AK27: =AK26*AK19 -> 204.21764
B28: 6 | C28: 2023 | D28: Regulatory Approval | F28: % of early stage patient receive chemo | G28: 0.8 | H28: =G28+0.005 -> 0.805 | I28: =H28+0.005 -> 0.81 | J28: =I28+0.005 -> 0.815 | K28: =J28+0.005 -> 0.82 | L28: =K28+0.005 -> 0.825 | M28: =L28+0.005 -> 0.83 | N28: =M28+0.005 -> 0.835 | O28: =N28+0.005 -> 0.84 | ... AK28: =AJ28+0.005 -> 0.95
B29: 7 | C29: 2024 | D29: Commercialization | F29: # of post-surgery chemo case ('000) | G29: =G28*G27 -> 14.658031 | H29: =H28*H27 -> 16.223 | I29: =I28*I27 -> 17.9291 | J29: =J28*J27 -> 19.778679 | K29: =K28*K27 -> 21.79929 | L29: =L28*L27 -> 23.997618 | M29: =M28*M27 -> 26.383626 | N29: =N28*N27 -> 28.95082 | ... AK29: =AK28*AK27 -> 194.00676
F31: Patient pool for chemo/targeted therapies ('000) | G31: =G24+G29 -> 50.386981 | H31: =H24+H29 -> 54.079249 | I31: =I24+I29 -> 58.025685 | J31: =J24+J29 -> 62.213565 | K31: =K24+K29 -> 66.708761 | L31: =L24+L29 -> 71.508054 | M31: =M24+M29 -> 76.618131 | N31: =N24+N29 -> 81.998431 | ... AK31: =AK24+AK29 -> 352.73957
F32: EGFR mutation (- or unclear) as % of total patient | G32: 0.6 | H32: 0.6 | I32: 0.6 | J32: 0.6 | K32: 0.6 | L32: 0.6 | M32: 0.6 | N32: 0.6 | O32: 0.6 | P32: 0.6 | Q32: 0.6 | R32: 0.6 | S32: 0.6 | T32: 0.6 | U32: 0.6 | V32: 0.6 | W32: 0.6 | X32: 0.6 | Y32: 0.6 | Z32: 0.6 | AA32: 0.6 | AB32: 0.6 | AC32: 0.6 | AD32: 0.6 | AE32: 0.6 | AF32: 0.6 | AG32: 0.6 | AH32: 0.6 | AI32: 0.6 | AJ32: 0.6 | AK32: 0.6
B33: Conditional Probabilities of Success | F33: Treatment rate | G33: 0.8 | H33: =G33+0.01 -> 0.81 | I33: =H33+0.01 -> 0.82 | J33: =I33+0.01 -> 0.83 | K33: =J33+0.01 -> 0.84 | L33: =K33+0.01 -> 0.85 | M33: =L33+0.01 -> 0.86 | N33: =M33+0.01 -> 0.87 | O33: =N33+0.01 -> 0.88 | ... Z33: =Y33+0.01 -> 0.99 | AA33: =Z33 -> 0.99 | AB33: =AA33 -> 0.99 | AC33: =AB33 -> 0.99 | AD33: =AC33 -> 0.99 | AE33: =AD33 -> 0.99 | AF33: =AE33 -> 0.99 | AG33: =AF33 -> 0.99 | AH33: =AG33 -> 0.99 | ... AK33: =AJ33 -> 0.99
B34: =B22 -> Stage No. | F34: Treated patients ('000) | G34: =G31*G32*G33 -> 24.185751 | H34: =H31*H32*H33 -> 26.282515 | I34: =I31*I32*I33 -> 28.548637 | J34: =J31*J32*J33 -> 30.982355 | K34: =K31*K32*K33 -> 33.621216 | L34: =L31*L32*L33 -> 36.469108 | M34: =M31*M32*M33 -> 39.534956 | N34: =N31*N32*N33 -> 42.803181 | ... AK34: =AK31*AK32*AK33 -> 209.5273
B35: =B23 -> 1 | C35: 0.9 | D35: =D23 -> Pre-clinical
B36: =B24 -> 2 | C36: 1 | D36: =D24 -> IND Filing | F36: % of patients received EGFR-TKIs | G36: 0.6 | H36: 0.6 | I36: 0.6 | J36: 0.6 | K36: 0.6 | L36: 0.6 | M36: 0.6 | N36: 0.6 | O36: 0.6 | P36: 0.6 | Q36: 0.6 | R36: 0.6 | S36: 0.6 | T36: 0.6 | U36: 0.6 | V36: 0.6 | W36: 0.6 | X36: 0.6 | Y36: 0.6 | Z36: 0.6 | AA36: 0.6 | AB36: 0.6 | AC36: 0.6 | AD36: 0.6 | AE36: 0.6 | AF36: 0.6 | AG36: 0.6 | AH36: 0.6 | AI36: 0.6 | AJ36: 0.6 | AK36: 0.6
B37: =B25 -> 3 | C37: 0.695 | D37: =D25 -> Phase 1 | F37: # of patients received EGFR-TKIs | G37: =G36*G34 -> 14.51145 | H37: =H36*H34 -> 15.769509 | I37: =I36*I34 -> 17.129182 | J37: =J36*J34 -> 18.589413 | K37: =K36*K34 -> 20.172729 | L37: =L36*L34 -> 21.881465 | M37: =M36*M34 -> 23.720973 | N37: =N36*N34 -> 25.681909 | ... AK37: =AK36*AK34 -> 125.71638
B38: =B26 -> 4 | C38: 0.427 | D38: =D26 -> Phase 2
B39: =B27 -> 5 | C39: 0.727 | D39: =D27 -> Phase 3 | F39: % of patients develped MET amplification | G39: 0.2 | H39: 0.2 | I39: 0.2 | J39: 0.2 | K39: 0.2 | L39: 0.2 | M39: 0.2 | N39: 0.2 | O39: 0.2 | P39: 0.2 | Q39: 0.2 | R39: 0.2 | S39: 0.2 | T39: 0.2 | U39: 0.2 | V39: 0.2 | W39: 0.2 | X39: 0.2 | Y39: 0.2 | Z39: 0.2 | AA39: 0.2 | AB39: 0.2 | AC39: 0.2 | AD39: 0.2 | AE39: 0.2 | AF39: 0.2 | AG39: 0.2 | AH39: 0.2 | AI39: 0.2 | AJ39: 0.2 | AK39: 0.2
B40: =B28 -> 6 | C40: 0.887 | D40: =D28 -> Regulatory Approval | F40: # of patients develped MET amplification | G40: =G39*G37 -> 2.9022901 | H40: =H39*H37 -> 3.1539018 | I40: =I39*I37 -> 3.4258364 | J40: =J39*J37 -> 3.7178826 | K40: =K39*K37 -> 4.0345459 | L40: =L39*L37 -> 4.3762929 | M40: =M39*M37 -> 4.7441947 | N40: =N39*N37 -> 5.1363817 | ... AK40: =AK39*AK37 -> 25.143276
B41: =B29 -> 7 | C41: 1 | D41: =D29 -> Commercialization
F42: Apollomics's c-met inhibitor's mkt share | G42: 0 | H42: 0 | I42: 0 | J42: 0 | K42: 0 | L42: 0 | M42: 0 | N42: 0 | O42: 0 | P42: 0 | Q42: 0 | R42: 0 | S42: 0 | T42: 0 | U42: 0.05 | V42: 0.15 | W42: 0.25 | X42: 0.35 | Y42: 0.45 | Z42: 0.5 | AA42: =Z42 -> 0.5 | AB42: =AA42 -> 0.5 | AC42: =AB42 -> 0.5 | AD42: =AC42 -> 0.5 | AE42: =AD42 -> 0.5 | AF42: =AE42 -> 0.5 | AG42: =AF42 -> 0.5 | AH42: =AG42 -> 0.5 | ... AK42: =AJ42 -> 0.5
B43: Cumulative Probabilities of cash outflow | F43: # of exChina patients on APL101 ('000) | G43: =G42*G40 -> 0 | H43: =H42*H40 -> 0 | I43: =I42*I40 -> 0 | J43: =J42*J40 -> 0 | K43: =K42*K40 -> 0 | L43: =L42*L40 -> 0 | M43: =M42*M40 -> 0 | N43: =N42*N40 -> 0 | ... AK43: =AK42*AK40 -> 12.571638
B44: =B22 -> Stage No.
B45: =B23 -> 1 | C45: 1 | D45: =D23 -> Pre-clinical | F45: PoS: | G45: 0.4
B46: =B24 -> 2 | C46: =IF(D19=D35,C35,1) -> 1 | D46: =D24 -> IND Filing | F46: Total # of exChina patients on APL101 ('000) | G46: =G43 -> 0 | H46: =H43 -> 0 | I46: =I43 -> 0 | J46: =J43 -> 0 | K46: =K43 -> 0 | L46: =L43 -> 0 | M46: =M43 -> 0 | N46: =N43 -> 0 | ... AK46: =AK43 -> 12.571638
B47: =B25 -> 3 | C47: =IF(D19=D35,C35*C36,IF(D19=D36,C36,1)) -> 1 | D47: =D25 -> Phase 1 | F47: 200mg (2 dosages) daily (proxy: Tabrecta)
B48: =B26 -> 4 | C48: =IF(D19=D35,C35*C36*C37,IF(D19=D36,C36*C37,IF(D19=D37,C37,1))) -> 1 | D48: =D26 -> Phase 2 | F48: Unit Price | Q48: 170 | R48: =Q48*(1+R49) -> 164.9 | S48: =R48*(1+S49) -> 159.953 | T48: =S48*(1+T49) -> 155.15441 | U48: =T48*(1+U49) -> 150.49978 | V48: =U48*(1+V49) -> 145.98478 | W48: =V48*(1+W49) -> 141.60524 | X48: =W48*(1+X49) -> 137.35708 | Y48: =X48*(1+Y49) -> 133.23637 | ... AK48: =AJ48*(1+AK49) -> 37.629887
B49: =B27 -> 5 | C49: =IF(D19=D35,C35*C36*C37*C38,IF(D19=D36,C36*C37*C38,IF(D19=D37,C37*C38,IF(D19=D38,C38,1)))) -> 0.427 | D49: =D27 -> Phase 3 | F49: y/y growth | Q49: -0.03 | R49: -0.03 | S49: -0.03 | T49: -0.03 | U49: -0.03 | V49: -0.03 | W49: -0.03 | X49: -0.03 | Y49: -0.03 | Z49: -0.1 | AA49: -0.1 | AB49: -0.1 | AC49: -0.1 | AD49: -0.1 | AE49: -0.1 | AF49: -0.1 | AG49: -0.1 | AH49: -0.1 | AI49: -0.1 | AJ49: -0.1 | AK49: -0.1
B50: =B28 -> 6 | C50: =IF(D19=D35,C35*C36*C37*C38*C39,IF(D19=D36,C36*C37*C38*C39,IF(D19=D37,C37*C38*C39,IF(D19=D38,C38*C39,IF(D19=D39,C39,1))))) -> 0.310429 | D50: =D28 -> Regulatory Approval | F50: Dosage | Q50: 2 | R50: 2 | S50: 2 | T50: 2 | U50: 2 | V50: 2 | W50: 2 | X50: 2 | Y50: 2 | Z50: 2 | AA50: 2 | AB50: 2 | AC50: 2 | AD50: 2 | AE50: 2 | AF50: 2 | AG50: 2 | AH50: 2 | AI50: 2 | AJ50: 2 | AK50: 2
F51: Duration (1 year) | Q51: =13*4*7 -> 364 | R51: =13*4*7 -> 364 | S51: =13*4*7 -> 364 | T51: =13*4*7 -> 364 | U51: =13*4*7 -> 364 | V51: =13*4*7 -> 364 | W51: =13*4*7 -> 364 | X51: =13*4*7 -> 364 | ... AK51: =13*4*7 -> 364
F52: Total # of dosages | Q52: =Q46*Q50*Q51 -> 0 | R52: =R46*R50*R51 -> 0 | S52: =S46*S50*S51 -> 0 | T52: =T46*T50*T51 -> 0 | U52: =U46*U50*U51 -> 318.99127 | V52: =V46*V50*V51 -> 1031.2705 | W52: =W46*W50*W51 -> 1851.5915 | X52: =X46*X50*X51 -> 2791.592 | ... AK52: =AK46*AK50*AK51 -> 9152.1526
F53: Sales of APL101 (US$ mn) | Q53: =Q48*Q50*Q51*Q46*$G$45/1000 -> 0 | R53: =R48*R50*R51*R46*$G$45/1000 -> 0 | S53: =S48*S50*S51*S46*$G$45/1000 -> 0 | T53: =T48*T50*T51*T46*$G$45/1000 -> 0 | U53: =U48*U50*U51*U46*$G$45/1000 -> 19.203246 | V53: =V48*V50*V51*V46*$G$45/1000 -> 60.219922 | W53: =W48*W50*W51*W46*$G$45/1000 -> 104.87803 | X53: =X48*X50*X51*X46*$G$45/1000 -> 153.37797 | ... AK53: =AK48*AK50*AK51*AK46*$G$45/1000 -> 137.75779
B54: Valuation progress | F54: y/y growth | Q54: =Q53/P53-1 -> #DIV/0! | R54: =R53/Q53-1 -> #DIV/0! | S54: =S53/R53-1 -> #DIV/0! | T54: =T53/S53-1 -> #DIV/0! | U54: =U53/T53-1 -> #DIV/0! | V54: =V53/U53-1 -> 2.1359241 | W54: =W53/V53-1 -> 0.74158356 | X54: =X53/W53-1 -> 0.46244145 | ... AK54: =AK53/AJ53-1 -> -0.043157933
B55: Stage | C55: Year | D55: Prob of Commercialized
B56: =D23 -> Pre-clinical | C56: =C23 -> 0 | D56: =C35*C36*C37*C38*C39*C40*C41 -> 0.17223175 | F56: Annual treatment cost (US$) | Q56: =Q48*Q50*Q51 -> 123760
B57: =D24 -> IND Filing | C57: =C24 -> 0 | D57: =C36*C37*C38*C39*C40*C41 -> 0.19136861
B58: =D25 -> Phase 1 | C58: =C25 -> 0 | D58: =C37*C38*C39*C40*C41 -> 0.19136861 | F58: Renal cell cancer (RCC) | G58: 2010 | H58: 2011 | I58: 2012 | J58: 2013 | K58: 2014 | L58: 2015 | M58: 2016 | N58: 2017A | O58: 2018A | P58: 2019A | Q58: 2020E | R58: 2021E | S58: 2022E | T58: 2023E | U58: 2024E | V58: 2025E | W58: 2026E | X58: 2027E | Y58: 2028E | Z58: 2029E | AA58: 2030E | AB58: 2031E | AC58: 2032E | AD58: 2033E | AE58: 2034E | AF58: 2035E | AG58: 2036E | AH58: 2037E | AI58: 2038E | AJ58: 2039E | AK58: 2040E
B59: =D26 -> Phase 2 | C59: =C26 -> 2021 | D59: =C38*C39*C40*C41 -> 0.27535052 | F59: US
B60: =D27 -> Phase 3 | C60: =C27 -> 2022 | D60: =C39*C40*C41 -> 0.644849 | F60: RCC incidence rate (per 100 000) | G60: =H60/1.02 -> 16.122008 | H60: =I60/1.02 -> 16.444449 | I60: =J60/1.02 -> 16.773338 | J60: =K60/1.02 -> 17.108804 | K60: =L60/1.02 -> 17.45098 | L60: 17.8 | M60: 18 | N60: 18.3 | O60: 18.5 | P60: 19 | Q60: =P60*1.02 -> 19.38 | R60: =Q60*1.02 -> 19.7676 | S60: =R60*1.02 -> 20.162952 | T60: =S60*1.02 -> 20.566211 | U60: =T60*1.02 -> 20.977535 | V60: =U60*1.02 -> 21.397086 | W60: =V60*1.02 -> 21.825028 | X60: =W60*1.02 -> 22.261528 | ... AK60: =AJ60*1.02 -> 28.797661
B61: =D28 -> Regulatory Approval | C61: =C28 -> 2023 | D61: =C40*C41 -> 0.887 | F61: Annual Incidence ('000) | G61: =G60*G7/100 -> 49.868865 | H61: =H60*H7/100 -> 51.23381 | I61: =I60*I7/100 -> 52.639931 | J61: =J60*J7/100 -> 54.062746 | K61: =K60*K7/100 -> 55.546646 | L61: =L60*L7/100 -> 57.073059 | M61: =M60*M7/100 -> 58.129436 | N61: =N60*N7/100 -> 59.472354 | ... AK61: =AK60*AK7/100 -> 104.41755
B62: Commercialization | C62: =C29 -> 2024 | D62: =C41 -> 1
F63: Early stage I, II, III ('000) | G63: =G61*G64 -> 34.908206 | H63: =H61*H64 -> 36.222304 | I63: =I61*I64 -> 37.588596 | J63: =J61*J64 -> 38.990631 | K63: =K61*K64 -> 40.461444 | L63: =L61*L64 -> 41.989051 | M63: =M61*M64 -> 43.193897 | N63: =N61*N64 -> 44.633689 | ... AK63: =AK61*AK64 -> 98.517361
F64: % of patients diagnosed at early stage | G64: 0.7 | H64: =G64*1.01 -> 0.707 | I64: =H64*1.01 -> 0.71407 | J64: =I64*1.01 -> 0.7212107 | K64: =J64*1.01 -> 0.72842281 | L64: =K64*1.01 -> 0.73570704 | M64: =L64*1.01 -> 0.74306411 | N64: =M64*1.01 -> 0.75049475 | O64: =N64*1.01 -> 0.75799969 | ... AK64: =AJ64*1.01 -> 0.94349424
F66: # of patients on surgery ('000) | G66: =G67*G63 -> 32.604264 | H66: =H67*H63 -> 33.831632 | I66: =I67*I63 -> 35.107748 | J66: =J67*J63 -> 36.417249 | K66: =K67*K63 -> 37.790989 | L66: =L67*L63 -> 39.217774 | M66: =M67*M63 -> 40.3431 | N66: =N67*N63 -> 41.687865 | ... AK66: =AK67*AK63 -> 92.015215
F67: Treatment rate | G67: 0.934 | H67: 0.934 | I67: 0.934 | J67: 0.934 | K67: 0.934 | L67: 0.934 | M67: 0.934 | N67: 0.934 | O67: 0.934 | P67: 0.934 | Q67: 0.934 | R67: 0.934 | S67: 0.934 | T67: 0.934 | U67: 0.934 | V67: 0.934 | W67: 0.934 | X67: 0.934 | Y67: 0.934 | Z67: 0.934 | AA67: 0.934 | AB67: 0.934 | AC67: 0.934 | AD67: 0.934 | AE67: 0.934 | AF67: 0.934 | AG67: 0.934 | AH67: 0.934 | AI67: 0.934 | AJ67: 0.934 | AK67: 0.934
F68: Relapse ('000) | G68: =G69*G66 -> 8.151066 | H68: =H69*H66 -> 8.4579079 | I68: =I69*I66 -> 8.7769371 | J68: =J69*J66 -> 9.1043124 | K68: =K69*K66 -> 9.4477472 | L68: =L69*L66 -> 9.8044434 | M68: =M69*M66 -> 10.085775 | N68: =N69*N66 -> 10.421966 | ... AK68: =AK69*AK66 -> 23.003804
F69: Relapse rate | G69: 0.25 | H69: 0.25 | I69: 0.25 | J69: 0.25 | K69: 0.25 | L69: 0.25 | M69: 0.25 | N69: 0.25 | O69: 0.25 | P69: 0.25 | Q69: 0.25 | R69: 0.25 | S69: 0.25 | T69: 0.25 | U69: 0.25 | V69: 0.25 | W69: 0.25 | X69: 0.25 | Y69: 0.25 | Z69: 0.25 | AA69: 0.25 | AB69: 0.25 | AC69: 0.25 | AD69: 0.25 | AE69: 0.25 | AF69: 0.25 | AG69: 0.25 | AH69: 0.25 | AI69: 0.25 | AJ69: 0.25 | AK69: 0.25
F70: # of patients on follow-up treatment - anti-angiogenic therapy ('000) | G70: =G71*G68 -> 7.3359594 | H70: =H71*H68 -> 7.6121171 | I70: =I71*I68 -> 7.8992434 | J70: =J71*J68 -> 8.1938811 | K70: =K71*K68 -> 8.5029725 | L70: =L71*L68 -> 8.8239991 | M70: =M71*M68 -> 9.0771975 | N70: =N71*N68 -> 9.3797697 | ... AK70: =AK71*AK68 -> 20.703423
F71: Treatment rate | G71: 0.9 | H71: 0.9 | I71: 0.9 | J71: 0.9 | K71: 0.9 | L71: 0.9 | M71: 0.9 | N71: 0.9 | O71: 0.9 | P71: 0.9 | Q71: 0.9 | R71: 0.9 | S71: 0.9 | T71: 0.9 | U71: 0.9 | V71: 0.9 | W71: 0.9 | X71: 0.9 | Y71: 0.9 | Z71: 0.9 | AA71: 0.9 | AB71: 0.9 | AC71: 0.9 | AD71: 0.9 | AE71: 0.9 | AF71: 0.9 | AG71: 0.9 | AH71: 0.9 | AI71: 0.9 | AJ71: 0.9 | AK71: 0.9
F72: Relapse ('000) | G72: =G73*G70 -> 1.8339898 | H72: =H73*H70 -> 1.9030293 | I72: =I73*I70 -> 1.9748108 | J72: =J73*J70 -> 2.0484703 | K72: =K73*K70 -> 2.1257431 | L72: =L73*L70 -> 2.2059998 | M72: =M73*M70 -> 2.2692994 | N72: =N73*N70 -> 2.3449424 | ... AK72: =AK73*AK70 -> 5.1758559
F73: Relapse rate | G73: 0.25 | H73: 0.25 | I73: 0.25 | J73: 0.25 | K73: 0.25 | L73: 0.25 | M73: 0.25 | N73: 0.25 | O73: 0.25 | P73: 0.25 | Q73: 0.25 | R73: 0.25 | S73: 0.25 | T73: 0.25 | U73: 0.25 | V73: 0.25 | W73: 0.25 | X73: 0.25 | Y73: 0.25 | Z73: 0.25 | AA73: 0.25 | AB73: 0.25 | AC73: 0.25 | AD73: 0.25 | AE73: 0.25 | AF73: 0.25 | AG73: 0.25 | AH73: 0.25 | AI73: 0.25 | AJ73: 0.25 | AK73: 0.25
F75: Advanced stage IV ('000) | G75: =G76*G61 -> 14.96066 | H75: =H76*H61 -> 15.011506 | I75: =I76*I61 -> 15.051336 | J75: =J76*J61 -> 15.072115 | K75: =K76*K61 -> 15.085202 | L75: =L76*L61 -> 15.084008 | M75: =M76*M61 -> 14.935539 | N75: =N76*N61 -> 14.838665 | ... AK75: =AK76*AK61 -> 5.9001932
F76: % of patients diagnosed at advanced stage | G76: =1-G64 -> 0.3 | H76: =1-H64 -> 0.293 | I76: =1-I64 -> 0.28593 | J76: =1-J64 -> 0.2787893 | K76: =1-K64 -> 0.27157719 | L76: =1-L64 -> 0.26429296 | M76: =1-M64 -> 0.25693589 | N76: =1-N64 -> 0.24950525 | ... AK76: =1-AK64 -> 0.056505759
F77: # of patients on surgery ('000) | G77: =G78*G75 -> 7.4803298 | H77: =H78*H75 -> 7.5057532 | I77: =I78*I75 -> 7.5256678 | J77: =J78*J75 -> 7.5360576 | K77: =K78*K75 -> 7.5426012 | L77: =L78*L75 -> 7.542004 | M77: =M78*M75 -> 7.4677693 | N77: =N78*N75 -> 7.4193323 | ... AK77: =AK78*AK75 -> 2.9500966
F78: Treatment rate | G78: 0.5 | H78: 0.5 | I78: 0.5 | J78: 0.5 | K78: 0.5 | L78: 0.5 | M78: 0.5 | N78: 0.5 | O78: 0.5 | P78: 0.5 | Q78: 0.5 | R78: 0.5 | S78: 0.5 | T78: 0.5 | U78: 0.5 | V78: 0.5 | W78: 0.5 | X78: 0.5 | Y78: 0.5 | Z78: 0.5 | AA78: 0.5 | AB78: 0.5 | AC78: 0.5 | AD78: 0.5 | AE78: 0.5 | AF78: 0.5 | AG78: 0.5 | AH78: 0.5 | AI78: 0.5 | AJ78: 0.5 | AK78: 0.5
F79: Relapse ('000) | G79: =G80*G77 -> 5.2362308 | H79: =H80*H77 -> 5.2540272 | I79: =I80*I77 -> 5.2679674 | J79: =J80*J77 -> 5.2752403 | K79: =K80*K77 -> 5.2798208 | L79: =L80*L77 -> 5.2794028 | M79: =M80*M77 -> 5.2274385 | N79: =N80*N77 -> 5.1935326 | ... AK79: =AK80*AK77 -> 2.0650676
F80: Relapse rate | G80: 0.7 | H80: 0.7 | I80: 0.7 | J80: 0.7 | K80: 0.7 | L80: 0.7 | M80: 0.7 | N80: 0.7 | O80: 0.7 | P80: 0.7 | Q80: 0.7 | R80: 0.7 | S80: 0.7 | T80: 0.7 | U80: 0.7 | V80: 0.7 | W80: 0.7 | X80: 0.7 | Y80: 0.7 | Z80: 0.7 | AA80: 0.7 | AB80: 0.7 | AC80: 0.7 | AD80: 0.7 | AE80: 0.7 | AF80: 0.7 | AG80: 0.7 | AH80: 0.7 | AI80: 0.7 | AJ80: 0.7 | AK80: 0.7
F81: # of patients on follow-up treatment - anti-angiogenic therapy ('000) | G81: =G82*G79 -> 4.7126077 | H81: =H82*H79 -> 4.7286245 | I81: =I82*I79 -> 4.7411707 | J81: =J82*J79 -> 4.7477163 | K81: =K82*K79 -> 4.7518387 | L81: =L82*L79 -> 4.7514625 | M81: =M82*M79 -> 4.7046947 | N81: =N82*N79 -> 4.6741794 | ... AK81: =AK82*AK79 -> 1.8585609
F82: Treatment rate | G82: 0.9 | H82: 0.9 | I82: 0.9 | J82: 0.9 | K82: 0.9 | L82: 0.9 | M82: 0.9 | N82: 0.9 | O82: 0.9 | P82: 0.9 | Q82: 0.9 | R82: 0.9 | S82: 0.9 | T82: 0.9 | U82: 0.9 | V82: 0.9 | W82: 0.9 | X82: 0.9 | Y82: 0.9 | Z82: 0.9 | AA82: 0.9 | AB82: 0.9 | AC82: 0.9 | AD82: 0.9 | AE82: 0.9 | AF82: 0.9 | AG82: 0.9 | AH82: 0.9 | AI82: 0.9 | AJ82: 0.9 | AK82: 0.9
F83: Relapse ('000) | G83: =G84*G81 -> 1.1781519 | H83: =H84*H81 -> 1.1821561 | I83: =I84*I81 -> 1.1852927 | J83: =J84*J81 -> 1.1869291 | K83: =K84*K81 -> 1.1879597 | L83: =L84*L81 -> 1.1878656 | M83: =M84*M81 -> 1.1761737 | N83: =N84*N81 -> 1.1685448 | ... AK83: =AK84*AK81 -> 0.46464021
F84: Relapse rate | G84: 0.25 | H84: 0.25 | I84: 0.25 | J84: 0.25 | K84: 0.25 | L84: 0.25 | M84: 0.25 | N84: 0.25 | O84: 0.25 | P84: 0.25 | Q84: 0.25 | R84: 0.25 | S84: 0.25 | T84: 0.25 | U84: 0.25 | V84: 0.25 | W84: 0.25 | X84: 0.25 | Y84: 0.25 | Z84: 0.25 | AA84: 0.25 | AB84: 0.25 | AC84: 0.25 | AD84: 0.25 | AE84: 0.25 | AF84: 0.25 | AG84: 0.25 | AH84: 0.25 | AI84: 0.25 | AJ84: 0.25 | AK84: 0.25
F86: Apollomics's c-met inhibitor's mkt share | G86: 0 | H86: 0 | I86: 0 | J86: 0 | K86: 0 | L86: 0 | M86: 0 | N86: 0 | O86: 0 | P86: 0 | Q86: 0 | R86: 0 | S86: 0 | T86: 0 | U86: 0.05 | V86: 0.15 | W86: 0.25 | X86: 0.35 | Y86: 0.45 | Z86: 0.5 | AA86: =Z86 -> 0.5 | AB86: =AA86 -> 0.5 | AC86: =AB86 -> 0.5 | AD86: =AC86 -> 0.5 | AE86: =AD86 -> 0.5 | AF86: =AE86 -> 0.5 | AG86: =AF86 -> 0.5 | AH86: =AG86 -> 0.5 | ... AK86: =AJ86 -> 0.5
F87: # of exChina patients on APL101 ('000) | G87: =G86*(G72+G83) -> 0 | H87: =H86*(H72+H83) -> 0 | I87: =I86*(I72+I83) -> 0 | J87: =J86*(J72+J83) -> 0 | K87: =K86*(K72+K83) -> 0 | L87: =L86*(L72+L83) -> 0 | M87: =M86*(M72+M83) -> 0 | N87: =N86*(N72+N83) -> 0 | ... AK87: =AK86*(AK72+AK83) -> 2.820248
F89: PoS: | G89: 0.4
F90: Total # of exChina patients on APL101 ('000) | G90: =G87 -> 0 | H90: =H87 -> 0 | I90: =I87 -> 0 | J90: =J87 -> 0 | K90: =K87 -> 0 | L90: =L87 -> 0 | M90: =M87 -> 0 | N90: =N87 -> 0 | ... AK90: =AK87 -> 2.820248
F91: 200mg (2 dosages) daily (proxy: Tabrecta)
F92: Unit Price | Q92: 170 | R92: =Q92*(1+R93) -> 164.9 | S92: =R92*(1+S93) -> 159.953 | T92: =S92*(1+T93) -> 155.15441 | U92: =T92*(1+U93) -> 150.49978 | V92: =U92*(1+V93) -> 145.98478 | W92: =V92*(1+W93) -> 141.60524 | X92: =W92*(1+X93) -> 137.35708 | Y92: =X92*(1+Y93) -> 133.23637 | ... AK92: =AJ92*(1+AK93) -> 37.629887
F93: y/y growth | Q93: -0.03 | R93: -0.03 | S93: -0.03 | T93: -0.03 | U93: -0.03 | V93: -0.03 | W93: -0.03 | X93: -0.03 | Y93: -0.03 | Z93: -0.1 | AA93: -0.1 | AB93: -0.1 | AC93: -0.1 | AD93: -0.1 | AE93: -0.1 | AF93: -0.1 | AG93: -0.1 | AH93: -0.1 | AI93: -0.1 | AJ93: -0.1 | AK93: -0.1
F94: Dosage | Q94: 2 | R94: 2 | S94: 2 | T94: 2 | U94: 2 | V94: 2 | W94: 2 | X94: 2 | Y94: 2 | Z94: 2 | AA94: 2 | AB94: 2 | AC94: 2 | AD94: 2 | AE94: 2 | AF94: 2 | AG94: 2 | AH94: 2 | AI94: 2 | AJ94: 2 | AK94: 2
F95: Duration (1 year) | Q95: =13*4*7 -> 364 | R95: =13*4*7 -> 364 | S95: =13*4*7 -> 364 | T95: =13*4*7 -> 364 | U95: =13*4*7 -> 364 | V95: =13*4*7 -> 364 | W95: =13*4*7 -> 364 | X95: =13*4*7 -> 364 | ... AK95: =13*4*7 -> 364
F96: Total # of dosages | Q96: =Q90*Q94*Q95 -> 0 | R96: =R90*R94*R95 -> 0 | S96: =S90*S94*S95 -> 0 | T96: =T90*T94*T95 -> 0 | U96: =U90*U94*U95 -> 147.97981 | V96: =V90*V94*V95 -> 453.30519 | W96: =W90*W94*W95 -> 771.40874 | X96: =X90*X94*X95 -> 1102.6444 | ... AK96: =AK90*AK94*AK95 -> 2053.1406
F97: Sales of APL101 (US$ mn) | Q97: =Q92*Q94*Q95*Q90*$G$45/1000 -> 0 | R97: =R92*R94*R95*R90*$G$45/1000 -> 0 | S97: =S92*S94*S95*S90*$G$45/1000 -> 0 | T97: =T92*T94*T95*T90*$G$45/1000 -> 0 | U97: =U92*U94*U95*U90*$G$45/1000 -> 8.9083714 | V97: =V92*V94*V95*V90*$G$45/1000 -> 26.470264 | W97: =W92*W94*W95*W90*$G$45/1000 -> 43.694208 | X97: =X92*X94*X95*X90*$G$45/1000 -> 60.582406 | ... AK97: =AK92*AK94*AK95*AK90*$G$45/1000 -> 30.903779
F98: y/y growth | Q98: =Q97/P97-1 -> #DIV/0! | R98: =R97/Q97-1 -> #DIV/0! | S98: =S97/R97-1 -> #DIV/0! | T98: =T97/S97-1 -> #DIV/0! | U98: =U97/T97-1 -> #DIV/0! | V98: =V97/U97-1 -> 1.9713921 | W98: =W97/V97-1 -> 0.65069029 | X98: =X97/W97-1 -> 0.38650884 | ... AK98: =AK97/AJ97-1 -> -0.081800945
F100: Annual treatment cost (US$) | Q100: =Q92*Q94*Q95 -> 123760
F102: Glioblastoma | G102: 2010 | H102: 2011 | I102: 2012 | J102: 2013 | K102: 2014 | L102: 2015 | M102: 2016 | N102: 2017A | O102: 2018E | P102: 2019E | Q102: 2020E | R102: 2021E | S102: 2022E | T102: 2023E | U102: 2024E | V102: 2025E | W102: 2026E | X102: 2027E | Y102: 2028E | Z102: 2029E | AA102: 2030E | AB102: 2031E | AC102: 2032E | AD102: 2033E | AE102: 2034E | AF102: 2035E | AG102: 2036E | AH102: 2037E | AI102: 2038E | AJ102: 2039E | AK102: 2040E
F103: US
F104: Incidence rate of brain cancer (per 100 000) | G104: =H104/1.03 -> 2.2992502 | H104: =I104/1.03 -> 2.3682277 | I104: =J104/1.03 -> 2.4392745 | J104: =K104/1.03 -> 2.5124528 | K104: =L104/1.03 -> 2.5878264 | L104: =M104/1.03 -> 2.6654611 | M104: =N104/1.03 -> 2.745425 | N104: =O104/1.03 -> 2.8277877 | O104: =P104/1.03 -> 2.9126214 | P104: 3 | Q104: =P104*1.03 -> 3.09 | R104: =Q104*1.03 -> 3.1827 | S104: =R104*1.03 -> 3.278181 | T104: =S104*1.03 -> 3.3765264 | U104: =T104*1.03 -> 3.4778222 | V104: =U104*1.03 -> 3.5821569 | W104: =V104*1.03 -> 3.6896216 | X104: =W104*1.03 -> 3.8003102 | ... AK104: =AJ104*1.03 -> 5.5808837
F105: Annual Incidence ('000) | G105: =G7*G104/100 -> 7.112079 | H105: =H7*H104/100 -> 7.3783762 | I105: =I7*I104/100 -> 7.6551994 | J105: =J7*J104/100 -> 7.9391928 | K105: =K7*K104/100 -> 8.2370774 | L105: =L7*L104/100 -> 8.5464057 | M105: =M7*M104/100 -> 8.8661114 | N105: =N7*N104/100 -> 9.1899012 | ... AK105: =AK7*AK104/100 -> 20.235749
F107: # of Glioblastoma (GBM) ('000) | G107: =G108*G105 -> 1.1094843 | H107: =H108*H105 -> 1.1510267 | I107: =I108*I105 -> 1.1942111 | J107: =J108*J105 -> 1.2385141 | K107: =K108*K105 -> 1.2849841 | L107: =L108*L105 -> 1.3332393 | M107: =M108*M105 -> 1.3831134 | N107: =N108*N105 -> 1.4336246 | ... AK107: =AK108*AK105 -> 3.1567768
F108: GBM % of brain cancer | G108: 0.156 | H108: 0.156 | I108: 0.156 | J108: 0.156 | K108: 0.156 | L108: 0.156 | M108: 0.156 | N108: 0.156 | O108: 0.156 | P108: 0.156 | Q108: 0.156 | R108: 0.156 | S108: 0.156 | T108: 0.156 | U108: 0.156 | V108: 0.156 | W108: 0.156 | X108: 0.156 | Y108: 0.156 | Z108: 0.156 | AA108: 0.156 | AB108: 0.156 | AC108: 0.156 | AD108: 0.156 | AE108: 0.156 | AF108: 0.156 | AG108: 0.156 | AH108: 0.156 | AI108: 0.156 | AJ108: 0.156 | AK108: 0.156
F110: Treatment - Radiation treatment (RT) + temozolomide (TMZ) ('000) | G110: =G107*G111 -> 0.88758746 | H110: =H107*H111 -> 0.92082135 | I110: =I107*I111 -> 0.95536889 | J110: =J107*J111 -> 0.99081127 | K110: =K107*K111 -> 1.0279873 | L110: =L107*L111 -> 1.0665914 | M110: =M107*M111 -> 1.1064907 | N110: =N107*N111 -> 1.1468997 | ... AK110: =AK107*AK111 -> 2.5254215
F111: Treatment rate | G111: 0.8 | H111: 0.8 | I111: 0.8 | J111: 0.8 | K111: 0.8 | L111: 0.8 | M111: 0.8 | N111: 0.8 | O111: 0.8 | P111: 0.8 | Q111: 0.8 | R111: 0.8 | S111: 0.8 | T111: 0.8 | U111: 0.8 | V111: 0.8 | W111: 0.8 | X111: 0.8 | Y111: 0.8 | Z111: 0.8 | AA111: 0.8 | AB111: 0.8 | AC111: 0.8 | AD111: 0.8 | AE111: 0.8 | AF111: 0.8 | AG111: 0.8 | AH111: 0.8 | AI111: 0.8 | AJ111: 0.8 | AK111: 0.8
F113: Relapse | G113: =G114*G110 -> 0.4881731 | H113: =H114*H110 -> 0.50645174 | I113: =I114*I110 -> 0.52545289 | J113: =J114*J110 -> 0.5449462 | K113: =K114*K110 -> 0.56539299 | L113: =L114*L110 -> 0.58662529 | M113: =M114*M110 -> 0.60856989 | N113: =N114*N110 -> 0.63079482 | ... AK113: =AK114*AK110 -> 1.3889818
F114: Relapse rate | G114: 0.55 | H114: 0.55 | I114: 0.55 | J114: 0.55 | K114: 0.55 | L114: 0.55 | M114: 0.55 | N114: 0.55 | O114: 0.55 | P114: 0.55 | Q114: 0.55 | R114: 0.55 | S114: 0.55 | T114: 0.55 | U114: 0.55 | V114: 0.55 | W114: 0.55 | X114: 0.55 | Y114: 0.55 | Z114: 0.55 | AA114: 0.55 | AB114: 0.55 | AC114: 0.55 | AD114: 0.55 | AE114: 0.55 | AF114: 0.55 | AG114: 0.55 | AH114: 0.55 | AI114: 0.55 | AJ114: 0.55 | AK114: 0.55
F116: % of R/R patients on APL101 w/RT and/or w/SRS/SRT and/or TMZ in combination with radiation therapy (RT) | G116: 0 | H116: 0 | I116: 0 | J116: 0 | K116: 0 | L116: 0 | M116: 0 | N116: 0 | O116: 0 | P116: 0 | Q116: 0 | R116: 0 | S116: 0 | T116: 0 | U116: 0.05 | V116: 0.15 | W116: 0.25 | X116: 0.35 | Y116: 0.45 | Z116: 0.5 | AA116: =Z116 -> 0.5 | AB116: =AA116 -> 0.5 | AC116: =AB116 -> 0.5 | AD116: =AC116 -> 0.5 | AE116: =AD116 -> 0.5 | AF116: =AE116 -> 0.5 | AG116: =AF116 -> 0.5 | AH116: =AG116 -> 0.5 | ... AK116: =AJ116 -> 0.5
...

Sheet Forecast
G4: 2018A | H4: 2019A | I4: 2020E | J4: 2021E | K4: 2022E | L4: 2023E | M4: 2024E | N4: 2025E | O4: 2026E | P4: 2027E | Q4: 2028E | R4: 2029E | S4: 2030E | T4: 2031 | U4: 2032 | V4: 2033 | W4: 2034 | X4: 2035 | Y4: 2036 | Z4: 2037 | AA4: 2038 | AB4: 2039 | AC4: 2040
B5: 销售费用/营收 | C5: Selling expenses as a % of revenue | L5: 0.3 | M5: 0.25 | N5: 0.2 | O5: 0.15 | P5: 0.1 | Q5: 0.1 | R5: 0.1 | S5: 0.1 | T5: 0.09 | U5: 0.08 | V5: 0.07 | W5: 0.06 | X5: 0.05 | Y5: 0.04 | Z5: 0.03 | AA5: 0.02 | AB5: 0.01 | AC5: 0.01
B6: 研发费用/营收 | C6: R&D expenses as a % of revenue | G6: =-ISBSCF!#REF!/ISBSCF!#REF! -> #REF! | H6: =-ISBSCF!D11/ISBSCF!D6 -> #DIV/0! | I6: 30 | J6: 30 | K6: 2.5 | L6: 1.9 | M6: 1.3 | N6: 0.85 | O6: 0.65 | P6: 0.55 | Q6: 0.5 | R6: 0.3 | S6: 0.25 | T6: 0.25 | U6: 0.25 | V6: 0.25 | W6: 0.25 | X6: 0.25 | Y6: 0.25 | Z6: 0.25 | AA6: 0.25 | AB6: 0.25 | AC6: 0.25
B7: 管理费用/营收 | C7: Mgmt expenses as a % of revenue | G7: =-ISBSCF!#REF!/ISBSCF!#REF! -> #REF! | H7: =-ISBSCF!D12/ISBSCF!D6 -> #DIV/0! | L7: 0.15 | M7: 0.15 | N7: 0.15 | O7: 0.15 | P7: 0.15 | Q7: 0.15 | R7: 0.15 | S7: 0.15 | T7: 0.15 | U7: 0.15 | V7: 0.15 | W7: 0.15 | X7: 0.15 | Y7: 0.15 | Z7: 0.15 | AA7: 0.15 | AB7: 0.15 | AC7: 0.15
B8: 税率 | C8: Tax rate | G8: =ISBSCF!#REF!/ISBSCF!#REF! -> #REF! | H8: =ISBSCF!D23/ISBSCF!D22 -> 0.0033441161 | I8: =H8 -> 0.0033441161 | J8: =I8 -> 0.0033441161 | K8: =J8 -> 0.0033441161 | L8: =K8 -> 0.0033441161 | M8: =L8 -> 0.0033441161 | N8: =M8 -> 0.0033441161 | O8: =N8 -> 0.0033441161 | P8: =O8 -> 0.0033441161 | ... AC8: =AB8 -> 0.0033441161
C12: #NAME? | H12: 0 | I12: =H12+I17*I$44*I$49 -> 0 | J12: =I12+J17*J$44*J$49 -> 0 | K12: =J12+K17*K$44*K$49 -> 0 | L12: =K12+L17*L$44*L$49 -> 0 | M12: =L12+M17*M$44*M$49 -> 0 | N12: =M12+N17*N$44*N$49 -> 0 | O12: =N12+O17*O$44*O$49 -> 0 | P12: =O12+P17*P$44*P$49 -> 0 | ... AC12: =AB12+AC17*AC$44*AC$49 -> 0
C13: #NAME? | H13: 0 | I13: =H13+I18*I$44*I$49 -> 0 | J13: =I13+J18*J$44*J$49 -> 0 | K13: =J13+K18*K$44*K$49 -> 0 | L13: =K13+L18*L$44*L$49 -> 0 | M13: =L13+M18*M$44*M$49 -> 0 | N13: =M13+N18*N$44*N$49 -> 0 | O13: =N13+O18*O$44*O$49 -> 0 | P13: =O13+P18*P$44*P$49 -> 0 | ... AC13: =AB13+AC18*AC$44*AC$49 -> 0
C14: Debt | G14: 0 | H14: 0 | I14: 0 | J14: 0 | K14: 0 | L14: 0 | M14: 0 | N14: 0 | O14: 0 | P14: 0 | Q14: 0 | R14: 0 | S14: 0 | T14: 0 | U14: 0 | V14: 0 | W14: 0 | X14: 0 | Y14: 0 | Z14: 0 | AA14: 0 | AB14: 0 | AC14: 0
C16: Debt mix
C17: =C12 -> #NAME? | G17: =IFERROR(G12/G$14,"") | H17: 0 | I17: =H17 -> 0 | J17: =I17 -> 0 | K17: =AVERAGE(H17:J17) -> 0 | L17: =AVERAGE(I17:K17) -> 0 | M17: =AVERAGE(J17:L17) -> 0 | N17: =AVERAGE(K17:M17) -> 0 | O17: =AVERAGE(L17:N17) -> 0 | P17: =AVERAGE(M17:O17) -> 0 | Q17: =AVERAGE(N17:P17) -> 0 | R17: =AVERAGE(O17:Q17) -> 0 | ... AC17: =AVERAGE(Z17:AB17) -> 0
C18: =C13 -> #NAME? | G18: =IFERROR(G13/G$14,"") | H18: 0 | I18: 0 | J18: =I18 -> 0 | K18: =J18 -> 0 | L18: =K18 -> 0 | M18: =L18 -> 0 | N18: =M18 -> 0 | O18: =N18 -> 0 | P18: =O18 -> 0 | Q18: =P18 -> 0 | ... AC18: =AB18 -> 0
B21: Assumed ST borrowings to repay within a year | C21: Debt repayment | G21: =ISBSCF!#REF! -> #REF! | H21: =ISBSCF!#REF! -> #REF! | I21: =H12 -> 0 | J21: =I12 -> 0 | K21: =J12 -> 0 | L21: =K12 -> 0 | M21: =L12 -> 0 | N21: =M12 -> 0 | O21: =N12 -> 0 | P21: =O12 -> 0 | ... AC21: =AB12 -> 0
B22: Issuance for CapEx | C22: Debt issuance | H22: =H21+H14-G14 -> #REF! | I22: =I21+I14-H14 -> 0 | J22: =J21+J14-I14 -> 0 | K22: =K21+K14-J14 -> 0 | L22: =L21+L14-K14 -> 0 | M22: =M21+M14-L14 -> 0 | N22: =N21+N14-M14 -> 0 | O22: =O21+O14-N14 -> 0 | ... AC22: =AC21+AC14-AB14 -> 0
C24: Cost of debt | G24: =G34/AVERAGE(F14,G14) -> #REF! | H24: =H34/AVERAGE(G14,H14) -> #DIV/0! | I24: 0 | J24: 0.02 | K24: 0.02 | L24: =K24 -> 0.02 | M24: =L24 -> 0.02 | N24: =M24 -> 0.02 | O24: =N24 -> 0.02 | P24: =O24 -> 0.02 | Q24: =P24 -> 0.02 | R24: =Q24 -> 0.02 | S24: =R24 -> 0.02 | ... AC24: =AB24 -> 0.02
C25: Interest income % | G25: =G35/AVERAGE(ISBSCF!#REF!) -> #REF! | H25: =H35/AVERAGE(ISBSCF!D32:D33) -> 0 | I25: 0.02 | J25: 0.02 | K25: 0.02 | L25: 0.02 | M25: 0.02 | N25: 0.02 | O25: 0.02 | P25: 0.02 | Q25: 0.02 | R25: 0.02 | S25: 0.02 | T25: 0.02 | U25: 0.02 | V25: 0.02 | W25: 0.02 | X25: 0.02 | Y25: 0.02 | Z25: 0.02 | AA25: 0.02 | AB25: 0.02 | AC25: 0.02
C27: Cash | G27: =ISBSCF!#REF! -> #REF! | H27: =ISBSCF!D38 -> 38.487 | I27: =ISBSCF!E38 -> #REF! | J27: =ISBSCF!F38 -> #REF! | K27: =ISBSCF!G38 -> #REF! | L27: =ISBSCF!H38 -> #REF! | M27: =ISBSCF!I38 -> #REF! | N27: =ISBSCF!J38 -> #REF! | O27: =ISBSCF!K38 -> #REF! | ... AC27: =ISBSCF!Y38 -> #REF!
B28: Forecast min cash balance as a % of revenue | C28: Cash as a % of revenue | G28: =G27/ISBSCF!#REF! -> #REF! | H28: =H27/ISBSCF!D6 -> #DIV/0! | I28: =H28 -> #DIV/0! | J28: =I28 -> #DIV/0! | K28: =J28 -> #DIV/0! | L28: =K28 -> #DIV/0! | M28: =L28 -> #DIV/0! | N28: =M28 -> #DIV/0! | O28: =N28 -> #DIV/0! | P28: =O28 -> #DIV/0! | ... AC28: =AB28 -> #DIV/0!
C29: Min cash balance required | H29: =H28*ISBSCF!D6 -> #DIV/0! | I29: =I28*ISBSCF!E6 -> #DIV/0! | J29: =J28*ISBSCF!F6 -> #DIV/0! | K29: =K28*ISBSCF!G6 -> #DIV/0! | L29: =L28*ISBSCF!H6 -> #DIV/0! | M29: =M28*ISBSCF!I6 -> #DIV/0! | N29: =N28*ISBSCF!J6 -> #DIV/0! | O29: =O28*ISBSCF!K6 -> #DIV/0! | ... AC29: =AC28*ISBSCF!Y6 -> #DIV/0!
B33: 财务费用 | C33: Financial expenses
B34: 利息支出 | C34: Interest expense | G34: =ISBSCF!#REF! -> #REF! | H34: =ISBSCF!D19 -> -0.046 | I34: =AVERAGE(H14,I14)*I24 -> 0 | J34: =AVERAGE(I14,J14)*J24 -> 0 | K34: =AVERAGE(J14,K14)*K24 -> 0 | L34: =AVERAGE(K14,L14)*L24 -> 0 | M34: =AVERAGE(L14,M14)*M24 -> 0 | N34: =AVERAGE(M14,N14)*N24 -> 0 | O34: =AVERAGE(N14,O14)*O24 -> 0 | P34: =AVERAGE(O14,P14)*P24 -> 0 | ... AC34: =AVERAGE(AB14,AC14)*AC24 -> 0
B35: 减：利息收入 | C35: Interest income | G35: =ISBSCF!#REF! -> #REF! | H35: =ISBSCF!D20 -> 0 | I35: =H27*I25 -> 0.76974 | J35: =I27*J25 -> #REF! | K35: =J27*K25 -> #REF! | L35: =K27*L25 -> #REF! | M35: =L27*M25 -> #REF! | N35: =M27*N25 -> #REF! | O35: =N27*O25 -> #REF! | P35: =O27*P25 -> #REF! | ... AC35: =AB27*AC25 -> #REF!
B36: 其他 | C36: Others | G36: 0 | H36: 0
B37: 合计 | C37: Total | G37: =G34+G35+G36 -> #REF! | H37: =H34+H35+H36 -> -0.046 | I37: =I34+I35+I36 -> 0.76974 | J37: =J34+J35+J36 -> #REF! | K37: =K34+K35+K36 -> #REF! | L37: =L34+L35+L36 -> #REF! | M37: =M34+M35+M36 -> #REF! | N37: =N34+N35+N36 -> #REF! | ... AC37: =AC34+AC35+AC36 -> #REF!
C44: CapEx | G44: =-ISBSCF!#REF! -> #REF! | H44: =-(ISBSCF!D97+ISBSCF!D96) -> 0.857 | I44: =-(ISBSCF!E97+ISBSCF!E96) -> 10.313 | J44: =-(ISBSCF!F97+ISBSCF!F96) -> 10.357 | K44: =-(ISBSCF!G97+ISBSCF!G96) -> 10.357 | L44: =-(ISBSCF!H97+ISBSCF!H96) -> 10.357 | M44: =-(ISBSCF!I97+ISBSCF!I96) -> 10.357 | N44: =-(ISBSCF!J97+ISBSCF!J96) -> 10.357 | O44: =-(ISBSCF!K97+ISBSCF!K96) -> 10.357 | ... AC44: =-(ISBSCF!Y97+ISBSCF!Y96) -> 10.357
C45: as a % of PPE, intangible assets and LT deferred expenses | G45: =G44/SUM(G68,G95) -> #REF! | H45: =H44/SUM(H68,H95) -> 0.95434298 | I45: =I44/SUM(I68,I95) -> 6.160693 | J45: =J44/SUM(J68,J95) -> 0.94205931 | K45: =K44/SUM(K68,K95) -> 0.53624314 | L45: =L44/SUM(L68,L95) -> 0.38886386 | M45: =M44/SUM(M68,M95) -> 0.31428658 | N45: =N44/SUM(N68,N95) -> 0.27060145 | ... AC45: =AC44/SUM(AC68,AC95) -> 0.049775561
C46: as a % of revenue | G46: =G44/ISBSCF!#REF! -> #REF! | H46: =H44/ISBSCF!D6 -> #DIV/0! | I46: =I44/ISBSCF!E6 -> #REF! | J46: =J44/ISBSCF!F6 -> #REF! | K46: =K44/ISBSCF!G6 -> #REF! | L46: =L44/ISBSCF!H6 -> #REF! | M46: =M44/ISBSCF!I6 -> #REF! | N46: =N44/ISBSCF!J6 -> #REF! | O46: =O44/ISBSCF!K6 -> #REF! | ... AC46: =AC44/ISBSCF!Y6 -> #REF!
C48: CapEx from cash | H48: 0.95 | I48: =H48 -> 0.95 | J48: =I48 -> 0.95 | K48: =J48-10% -> 0.85 | L48: =K48-10% -> 0.75 | M48: =L48 -> 0.75 | N48: =M48 -> 0.75 | O48: =N48 -> 0.75 | P48: =O48 -> 0.75 | Q48: =P48 -> 0.75 | R48: =Q48 -> 0.75 | S48: =R48 -> 0.75 | T48: =S48 -> 0.75 | ... AC48: =AB48 -> 0.75
C49: CapEx from debt | H49: =1-H48 -> 0.05 | I49: =1-I48 -> 0.05 | J49: =1-J48 -> 0.05 | K49: =1-K48 -> 0.15 | L49: =1-L48 -> 0.25 | M49: =1-M48 -> 0.25 | N49: =1-N48 -> 0.25 | O49: =1-O48 -> 0.25 | ... AC49: =1-AC48 -> 0.25
C51: Account receivable days | H51: =AVERAGE(ISBSCF!D31:D31)/ISBSCF!D6*365 -> #DIV/0! | I51: 150 | J51: =I51-5 -> 145 | K51: =J51-5 -> 140 | L51: =K51-5 -> 135 | M51: =L51-5 -> 130 | N51: =M51 -> 130 | O51: =N51 -> 130 | P51: =O51 -> 130 | Q51: =P51 -> 130 | R51: =Q51 -> 130 | S51: =R51 -> 130 | T51: =S51 -> 130 | U51: =T51 -> 130 | ... AC51: =AB51 -> 130
C52: Inventory days | H52: =AVERAGE(ISBSCF!D32:D32)/ISBSCF!D6*365 -> #DIV/0! | I52: 200 | J52: =I52-5 -> 195 | K52: =J52-5 -> 190 | L52: =K52-5 -> 185 | M52: =L52-5 -> 180 | N52: =M52-5 -> 175 | O52: =N52-5 -> 170 | P52: =O52-5 -> 165 | Q52: =P52-5 -> 160 | ... S52: =R52-5 -> 150 | T52: =S52 -> 150 | U52: =T52 -> 150 | V52: =U52 -> 150 | W52: =V52 -> 150 | X52: =W52 -> 150 | Y52: =X52 -> 150 | Z52: =Y52 -> 150 | AA52: =Z52 -> 150 | ... AC52: =AB52 -> 150
C53: Account payable days | H53: =AVERAGE(ISBSCF!D52:D52)/ISBSCF!D6*365 -> #DIV/0! | I53: 180 | J53: =I53+3 -> 183 | K53: =J53+3 -> 186 | L53: =K53+3 -> 189 | M53: =L53+3 -> 192 | N53: =M53+3 -> 195 | O53: =N53+3 -> 198 | P53: =O53+3 -> 201 | Q53: =P53+3 -> 204 | ... T53: =S53+3 -> 213 | U53: =T53 -> 213 | V53: =U53 -> 213 | W53: =V53 -> 213 | X53: =W53 -> 213 | Y53: =X53 -> 213 | Z53: =Y53 -> 213 | AA53: =Z53 -> 213 | AB53: =AA53 -> 213 | AC53: =AB53 -> 213
C54: Cash conversion days | H54: =H51+H52-H53 -> #DIV/0! | I54: =I51+I52-I53 -> 170 | J54: =J51+J52-J53 -> 157 | K54: =K51+K52-K53 -> 144 | L54: =L51+L52-L53 -> 131 | M54: =M51+M52-M53 -> 118 | N54: =N51+N52-N53 -> 110 | O54: =O51+O52-O53 -> 102 | ... AC54: =AC51+AC52-AC53 -> 67
B66: 固定资产 | C66: fixed assets
B67: 一、账面原值： | C67: beginning value
B68: 1.期初余额 | C68: beginning balance | H68: 0.023 | I68: =H87 -> 0.336 | J68: =I76 -> 0.693 | K68: =J76 -> 1.05 | L68: =K76 -> 1.407 | M68: =L76 -> 1.764 | N68: =M76 -> 2.121 | O68: =N76 -> 2.478 | P68: =O76 -> 2.835 | Q68: =P76 -> 3.192 | ... AC68: =AB76 -> 7.476
B69: 2.本期增加金额 | C69: increase in this period | H69: 0.357 | I69: =H69 -> 0.357 | J69: =I69 -> 0.357 | K69: =J69 -> 0.357 | L69: =K69 -> 0.357 | M69: =L69 -> 0.357 | N69: =M69 -> 0.357 | O69: =N69 -> 0.357 | P69: =O69 -> 0.357 | ... AC69: =AB69 -> 0.357
B70: （1）购置 | C70: increase by purchasing | I70: =H70 -> 0 | J70: =I70 -> 0 | K70: =J70 -> 0 | L70: =K70 -> 0 | M70: =L70 -> 0 | N70: =M70 -> 0 | O70: =N70 -> 0 | P70: =O70 -> 0 | ... AC70: =AB70 -> 0
B71: （2）在建工程转入 | C71: increase by transfering from constrution in process
B72: （3）企业合并增加 | C72: increase by M&A | I72: 0 | J72: 0 | K72: 0 | L72: 0 | M72: 0 | N72: 0 | O72: 0 | P72: 0 | Q72: 0 | R72: 0 | S72: 0 | T72: 0 | U72: 0 | V72: 0 | W72: 0 | X72: 0 | Y72: 0 | Z72: 0 | AA72: 0 | AB72: 0 | AC72: 0
B73: (4) 汇率影响 | C73: influences of exchange rate movements | I73: 0 | J73: 0 | K73: 0 | L73: 0 | M73: 0 | N73: 0 | O73: 0 | P73: 0 | Q73: 0 | R73: 0 | S73: 0 | T73: 0 | U73: 0 | V73: 0 | W73: 0 | X73: 0 | Y73: 0 | Z73: 0 | AA73: 0 | AB73: 0 | AC73: 0
B74: 3.本期减少金额 | C74: decrease in this period
B75: （1)处置或报废 | C75: disposal or scrap | I75: =H75 -> 0 | J75: =I75 -> 0 | K75: =J75 -> 0 | L75: =K75 -> 0 | M75: =L75 -> 0 | N75: =M75 -> 0 | O75: =N75 -> 0 | P75: =O75 -> 0 | ... AC75: =AB75 -> 0
B76: 4.期末余额 | C76: ending balance | H76: =SUM(H68:H75) -> 0.38 | I76: =SUM(I68:I75) -> 0.693 | J76: =SUM(J68:J75) -> 1.05 | K76: =SUM(K68:K75) -> 1.407 | L76: =SUM(L68:L75) -> 1.764 | M76: =SUM(M68:M75) -> 2.121 | N76: =SUM(N68:N75) -> 2.478 | O76: =SUM(O68:O75) -> 2.835 | ... AC76: =SUM(AC68:AC75) -> 7.833
B77: 二、累计折旧 | C77: Accumulated depreciation | H77: =H78+H79 -> 0.044 | I77: =I78+I79 -> 0.044 | J77: =J78+J79 -> 0.044 | K77: =K78+K79 -> 0.044 | L77: =L78+L79 -> 0.044 | M77: =M78+M79 -> 0.044 | N77: =N78+N79 -> 0.044 | O77: =O78+O79 -> 0.044 | ... AC77: =AC78+AC79 -> 0.044
B78: 1.期初余额 | C78: beginning balance | H78: 0.005 | I78: =H78 -> 0.005 | J78: =I78 -> 0.005 | K78: =J78 -> 0.005 | L78: =K78 -> 0.005 | M78: =L78 -> 0.005 | N78: =M78 -> 0.005 | O78: =N78 -> 0.005 | P78: =O78 -> 0.005 | ... AC78: =AB78 -> 0.005
B79: 2.本期增加额 | C79: increase in this period | H79: 0.039 | I79: =AVERAGE(G79:H79) -> 0.039 | J79: =AVERAGE(H79:I79) -> 0.039 | K79: =J79 -> 0.039 | L79: =K79 -> 0.039 | M79: =L79 -> 0.039 | N79: =M79 -> 0.039 | O79: =N79 -> 0.039 | P79: =O79 -> 0.039 | Q79: =P79 -> 0.039 | R79: =Q79 -> 0.039 | ... AC79: =AB79 -> 0.039
B80: （1）计提 | C80: provision
B81: （2)汇率影响 | C81: influences of exchange rate movements | I81: 0 | J81: 0 | K81: 0 | L81: 0 | M81: 0 | N81: 0 | O81: 0 | P81: 0 | Q81: 0 | R81: 0
B82: 3.本期减少金额 | C82: decrease in this period | I82: =I83 -> 0 | J82: =J83 -> 0 | K82: =K83 -> 0 | L82: =L83 -> 0 | M82: =M83 -> 0 | N82: =N83 -> 0 | O82: =O83 -> 0 | P82: =P83 -> 0 | ... AC82: =AC83 -> 0
B83: （1)处置或报废 | C83: disposal or scrap
B84: 4.期末余额 | C84: ending balance | H84: =H76-H77 -> 0.336 | I84: =I76-I77 -> 0.649 | J84: =J76-J77 -> 1.006 | K84: =K76-K77 -> 1.363 | L84: =L76-L77 -> 1.72 | M84: =M76-M77 -> 2.077 | N84: =N76-N77 -> 2.434 | O84: =O76-O77 -> 2.791 | ... AC84: =AC76-AC77 -> 7.789
B85: 三、减值准备 | C85: increased provision
B86: 四、账面价值 | C86: book value
B87: 1.期末账面价值 | C87: end-of-term book value | G87: =ISBSCF!#REF! -> #REF! | H87: =ISBSCF!D40 -> 0.336 | I87: =I76-I77 -> 0.649 | J87: =J76-J77 -> 1.006 | K87: =K76-K77 -> 1.363 | L87: =L76-L77 -> 1.72 | M87: =M76-M77 -> 2.077 | N87: =N76-N77 -> 2.434 | O87: =O76-O77 -> 2.791 | P87: =P76-P77 -> 3.148 | ... AC87: =AC76-AC77 -> 7.789
B88: 2.期初账面价值 | C88: opening book value
C90: Depreciation as % of gross fixed assets | G90: =G79/F76 -> #DIV/0! | H90: =H79/G76 -> #DIV/0! | I90: =I79/H76 -> 0.10263158 | J90: =I90 -> 0.10263158 | K90: =J90 -> 0.10263158 | L90: =K90 -> 0.10263158 | M90: =L90 -> 0.10263158 | N90: =M90 -> 0.10263158 | O90: =N90 -> 0.10263158 | P90: =O90 -> 0.10263158 | Q90: =P90 -> 0.10263158 | ... AC90: =AB90 -> 0.10263158
B93: 无形资产 | C93: Intangible assets
B94: 一、账面原值： | C94: beginning value
B95: 1.期初余额 | C95: beginning balance | H95: 0.875 | I95: =H118 -> 1.338 | J95: =I118 -> 10.301 | K95: =J118 -> 18.264 | L95: =K118 -> 25.227 | M95: =L118 -> 31.19 | N95: =M118 -> 36.153 | O95: =N118 -> 40.116 | P95: =O118 -> 43.079 | ... AC95: =AB118 -> 200.598
B96: 2.本期增加金额 | C96: increase in this period | H96: 0.5 | I96: =SUM(I97:I101) -> 10 | J96: =SUM(J97:J101) -> 10 | K96: =SUM(K97:K101) -> 10 | L96: =SUM(L97:L101) -> 10 | M96: =SUM(M97:M101) -> 10 | N96: =SUM(N97:N101) -> 10 | O96: =SUM(O97:O101) -> 10 | P96: =SUM(P97:P101) -> 10 | ... AC96: =SUM(AC97:AC101) -> 30
B97: （1）购置 | C97: increase by purchasing | I97: 10 | J97: =I97 -> 10 | K97: =J97 -> 10 | L97: =K97 -> 10 | M97: =L97 -> 10 | N97: =M97 -> 10 | O97: =N97 -> 10 | P97: =O97 -> 10 | Q97: =P97 -> 10 | ... AC97: =AB97 -> 10
B98: （2）内部研发 | C98: Internal R&D | I98: 0 | J98: 0 | K98: 0 | L98: 0 | M98: 0 | N98: 0 | O98: 0 | P98: 0 | Q98: 0 | R98: 0 | S98: 0 | T98: 0 | U98: 0 | V98: 0 | W98: 0 | X98: 0 | Y98: 0 | Z98: 0 | AA98: 0 | AB98: 0 | AC98: 0
B99: （3）企业合并增加 | C99: increase by M&A in this period | I99: 0 | J99: 0 | K99: 0 | L99: 0 | M99: 0 | N99: 0 | O99: 0 | P99: 0 | Q99: 0 | R99: 0 | S99: 0 | T99: 0 | U99: 0 | V99: 0 | W99: 0 | X99: 0 | Y99: 0 | Z99: 0 | AA99: 0 | AB99: 0 | AC99: 0
B100: 3.本期减少金额 | C100: decrease in this period | I100: =I101 -> 0 | J100: =J101 -> 0 | K100: =K101 -> 0 | L100: =L101 -> 0 | M100: =M101 -> 0 | N100: =N101 -> 0 | O100: =O101 -> 0 | P100: =P101 -> 0 | ... AC100: =AC101 -> 10
B101: （1) 处置 | C101: disposal | I101: 0 | J101: 0 | K101: 0 | L101: 0 | M101: 0 | N101: 0 | O101: 0 | P101: 0 | Q101: 0 | R101: 0 | S101: 0 | T101: 1 | U101: 2 | V101: 3 | W101: 4 | X101: 5 | Y101: 6 | Z101: 7 | AA101: 8 | AB101: 9 | AC101: 10
B102: 4.期末余额 | C102: ending balance | H102: =SUM(H95:H101) -> 1.375 | I102: =I95+I96 -> 11.338 | J102: =J95+J96 -> 20.301 | K102: =K95+K96 -> 28.264 | L102: =L95+L96 -> 35.227 | M102: =M95+M96 -> 41.19 | N102: =N95+N96 -> 46.153 | O102: =O95+O96 -> 50.116 | P102: =P95+P96 -> 53.079 | ... AC102: =AC95+AC96 -> 230.598
B103: 二、累计摊销 | C103: accumulated amortization | H103: =H105+H104 -> 0.037 | I103: =I105+I104 -> 1.037 | J103: =J105+J104 -> 2.037 | K103: =K105+K104 -> 3.037 | L103: =L105+L104 -> 4.037 | M103: =M105+M104 -> 5.037 | N103: =N105+N104 -> 6.037 | O103: =O105+O104 -> 7.037 | ... AC103: =AC105+AC104 -> -23.963
B104: 1.期初余额 | C104: beginning balance | H104: 0.017 | I104: =H110 -> 0.037 | J104: =I110 -> 1.037 | K104: =J110 -> 2.037 | L104: =K110 -> 3.037 | M104: =L110 -> 4.037 | N104: =M110 -> 5.037 | O104: =N110 -> 6.037 | P104: =O110 -> 7.037 | ... AC104: =AB110 -> -24.963
B105: 2.本期增加金额 | C105: increase in this period | H105: 0.02 | I105: 1 | J105: =I105 -> 1 | K105: =J105 -> 1 | L105: =K105 -> 1 | M105: =L105 -> 1 | N105: =M105 -> 1 | O105: =N105 -> 1 | P105: =O105 -> 1 | Q105: =P105 -> 1 | ... AC105: =AB105 -> 1
B106: （1）计提 | C106: provision
B107: （2)汇率影响 | C107: influences of exchange rate movements | I107: 0 | J107: 0 | K107: 0 | L107: 0 | M107: 0 | N107: 0 | O107: 0 | P107: 0 | Q107: 0 | R107: 0 | S107: 0 | T107: 1 | U107: 2 | V107: 3 | W107: 4 | X107: 5 | Y107: 6 | Z107: 7 | AA107: 8 | AB107: 9 | AC107: 10
B108: 3.本期减少金额 | C108: decrease in this period | I108: =I109 -> 0 | J108: =J109 -> 0 | K108: =K109 -> 0 | L108: =L109 -> 0 | M108: =M109 -> 0 | N108: =N109 -> 0 | O108: =O109 -> 0 | P108: =P109 -> 0 | ... AC108: =AC109 -> 10
B109: （1)处置 | C109: disposal | I109: 0 | J109: 0 | K109: 0 | L109: 0 | M109: 0 | N109: 0 | O109: 0 | P109: 0 | Q109: 0 | R109: 0 | S109: 0 | T109: 1 | U109: 2 | V109: 3 | W109: 4 | X109: 5 | Y109: 6 | Z109: 7 | AA109: 8 | AB109: 9 | AC109: 10
B110: 4.期末余额 | C110: ending balance | H110: =H104+H105-H108 -> 0.037 | I110: =I104+I105-I108 -> 1.037 | J110: =J104+J105-J108 -> 2.037 | K110: =K104+K105-K108 -> 3.037 | L110: =L104+L105-L108 -> 4.037 | M110: =M104+M105-M108 -> 5.037 | N110: =N104+N105-N108 -> 6.037 | O110: =O104+O105-O108 -> 7.037 | ... AC110: =AC104+AC105-AC108 -> -33.963
B111: 三、减值准备 | C111: increased provision
B112: 1.期初余额 | C112: beginning balance
B113: 2.本期增加额 | C113: increase in this period
B114: （1)计提 | C114: provision
B115: （2)汇率影响 | C115: influences of exchange rate movements
B116: 3.本期减少金额 | C116: decrease in this period
B117: （1)处置 | C117: disposal
B118: 4.期末余额 | C118: ending balance | G118: =G102-G105 -> 0 | H118: =H102-H103 -> 1.338 | I118: =I102-I103 -> 10.301 | J118: =J102-J103 -> 18.264 | K118: =K102-K103 -> 25.227 | L118: =L102-L103 -> 31.19 | M118: =M102-M103 -> 36.153 | N118: =N102-N103 -> 40.116 | O118: =O102-O103 -> 43.079 | ... AC118: =AC102-AC103 -> 254.561
B119: 四、账面价值 | C119: book value
B120: 1.期末账面价值 | C120: end-of-term book value | G120: =ISBSCF!#REF! -> #REF! | H120: =ISBSCF!D42 -> 1.338 | I120: =I118 -> 10.301 | J120: =J118 -> 18.264 | K120: =K118 -> 25.227 | L120: =L118 -> 31.19 | M120: =M118 -> 36.153 | N120: =N118 -> 40.116 | O120: =O118 -> 43.079 | P120: =P118 -> 45.042 | ... AC120: =AC118 -> 254.561
B121: 2.期初账面价值 | C121: opening book value
C123: Amortization as % of gross intangible assets | G123: =G104/G102 -> #DIV/0! | H123: =H103/H102 -> 0.026909091 | I123: =H123 -> 0.026909091 | J123: =I123 -> 0.026909091 | K123: =J123 -> 0.026909091 | L123: =K123 -> 0.026909091 | M123: =L123 -> 0.026909091 | N123: =M123 -> 0.026909091 | O123: =N123 -> 0.026909091 | P123: =O123 -> 0.026909091 | ... AC123: =AB123 -> 0.026909091
B126: 土地所有权 | C126: Right-of-use assets
B127: 一、账面原值 | C127: beginning value
B128: 1.期初余额 | C128: beginning balance | H128: 0.191 | I128: =H142 -> 1.674 | J128: =I142 -> 3.157 | K128: =J142 -> 4.64 | L128: =K142 -> 6.123 | M128: =L142 -> 7.606 | N128: =M142 -> 9.089 | O128: =N142 -> 10.572 | P128: =O142 -> 12.055 | ... AC128: =AB142 -> 35.054
B129: 2.本期增加 | C129: increase in this period | H129: 1.876 | I129: =H129 -> 1.876 | J129: =I129 -> 1.876 | K129: =J129 -> 1.876 | L129: =K129 -> 1.876 | M129: =L129 -> 1.876 | N129: =M129 -> 1.876 | O129: =N129 -> 1.876 | P129: =O129 -> 1.876 | ... AC129: =AB129 -> 1.876
B130: （1)企业合并形成的 | C130: increase by M&A in this period
B131: (2) 汇率变动影响 | C131: influences of exchange rate movements
B132: 3.本期减少 | C132: decrease in this period | I132: =I133 -> 0 | J132: =J133 -> 0 | K132: =K133 -> 0 | L132: =L133 -> 0 | M132: =M133 -> 0 | N132: =N133 -> 0 | O132: =O133 -> 0 | P132: =P133 -> 0 | ... AC132: =AC133 -> 10
B133: (1) 处置 | C133: disposal | I133: 0 | J133: 0 | K133: 0 | L133: 0 | M133: 0 | N133: 0 | O133: 0 | P133: 0 | Q133: 0 | R133: 0 | S133: 0 | T133: 1 | U133: 2 | V133: 3 | W133: 4 | X133: 5 | Y133: 6 | Z133: 7 | AA133: 8 | AB133: 9 | AC133: 10
B134: 4.期末余额 | C134: ending balance | H134: =H128+H129 -> 2.067 | I134: =I128+I129 -> 3.55 | J134: =J128+J129 -> 5.033 | K134: =K128+K129 -> 6.516 | L134: =L128+L129 -> 7.999 | M134: =M128+M129 -> 9.482 | N134: =N128+N129 -> 10.965 | O134: =O128+O129 -> 12.448 | ... AC134: =AC128+AC129 -> 36.93
B135: 二、累计折旧 | C135: Accumulated depreciation | H135: =H136+H137 -> 0.393 | I135: =I136+I137 -> 0.393 | J135: =J136+J137 -> 0.393 | K135: =K136+K137 -> 0.393 | L135: =L136+L137 -> 0.393 | M135: =M136+M137 -> 0.393 | N135: =N136+N137 -> 0.393 | O135: =O136+O137 -> 0.393 | ... AC135: =AC136+AC137 -> 0.083
B136: 1.期初余额 | C136: beginning balance | H136: 0.083 | I136: =H136 -> 0.083 | J136: =I136 -> 0.083 | K136: =J136 -> 0.083 | L136: =K136 -> 0.083 | M136: =L136 -> 0.083 | N136: =M136 -> 0.083 | O136: =N136 -> 0.083 | P136: =O136 -> 0.083 | ... AC136: =AB136 -> 0.083
B137: 2.本期增加额 | C137: increase in this period | H137: 0.31 | I137: =H137 -> 0.31 | J137: =I137 -> 0.31 | K137: =J137 -> 0.31 | L137: =K137 -> 0.31 | M137: =L137 -> 0.31 | N137: =M137 -> 0.31 | O137: =N137 -> 0.31 | P137: =O137 -> 0.31 | Q137: 0 | R137: =Q137 -> 0 | S137: =R137 -> 0 | T137: =S137 -> 0 | U137: =T137 -> 0 | V137: =U137 -> 0 | W137: =V137 -> 0 | X137: =W137 -> 0 | Y137: =X137 -> 0 | ... AC137: =AB137 -> 0
B138: （1)企业合并形成的 | C138: increase by M&A in this period
B139: (2) 汇率变动影响 | C139: influences of exchange rate movements
...
